Workbook
Name Slicer_borrowerbank: #N/A
Name Slicer_borrowervintagetier: #N/A
Name Slicer_employmentstatus: #N/A

Sheet Risk_Diagnostics_Hub
A1: repaymentstatusflag | B1: (All)
A2: The Banking Ecosystem Risk Test | E2: The Income & Employment Stability Test
A3: Row Labels | B3: NPL Ratio | E3: Row Labels | F3: Average of repaymentstatusflag
A4: Access Bank | B4: 0.23780488 | F4: 0.30425963 | J4: Total Capital Disbursed
A5: Diamond Bank | B5: 0.14351852 | E5: Contract | F5: 0 | J5: 77790000
A6: EcoBank | B6: 0.25862069 | E6: Permanent | F6: 0.20555556
A7: FCMB | B7: 0.25842697 | E7: Retired | F7: 0
A8: Fidelity Bank | B8: 0.22972973 | E8: Self-Employed | F8: 0.16245487 | J8: PORTFOLIO AT RISK (BAD LOANS)
A9: First Bank | B9: 0.22093023 | E9: Student | F9: 0.27027027 | J9: 952
A10: GT Bank | B10: 0.21623861 | E10: Unemployed | F10: 0.1627907
A11: Heritage Bank | B11: 0.16666667 | E11: Unknown Status | F11: 0.21747043
A12: Keystone Bank | B12: 0.21428571 | E12: Grand Total | F12: 0.21794872 | J12: Average of repaymentstatusflag
A13: Skye Bank | B13: 0.28 | J13: 0.21794872
A14: Stanbic IBTC | B14: 0.15384615
A15: Standard Chartered | B15: 0.076923077 | E15: The Pricing Appetite Test
A16: Sterling Bank | B16: 0.35714286 | E16: interest markup | F16: Badloans(count) | G16: NPL Ratio
A17: UBA | B17: 0.22846442 | E17: 0 | F17: 0 | G17: 0
A18: Union Bank | B18: 0.13333333 | E18: 0.025 | F18: 0 | G18: 0
A19: Unity Bank | B19: 0.2 | E19: 0.045 | F19: 0 | G19: 0
A20: Unspecified Bank | B20: 0.21747043 | E20: 0.05 | F20: 1 | G20: 0.021276596
A21: Wema Bank | B21: 0.10526316 | E21: 0.075 | F21: 1 | G21: 0.04
A22: Zenith Bank | B22: 0.22767857 | E22: 0.0875 | F22: 2 | G22: 0.28571429
A23: Grand Total | B23: 0.21794872 | E23: 0.09 | F23: 0 | G23: 0
E24: 0.1 | F24: 29 | G24: 0.097972973
E25: 0.1125 | F25: 33 | G25: 0.19186047
E26: 0.13333 | F26: 0 | G26: 0
A27: The Vintage Loyalty Test (Borrower Velocity) | E27: 0.135 | F27: 1 | G27: 0.25
A28: Row Labels | B28: NPL Ratio | E28: 0.14001 | F28: 0 | G28: 0
A29: 2. Early Repeat (2-3) | B29: 0.25496849 | E29: 0.15 | F29: 242 | G29: 0.20066335
A30: 3. High Velocity Loyalty (4+) | B30: 0.18481562 | E30: 0.2 | F30: 28 | G30: 0.20437956
A31: Grand Total | B31: 0.21794872 | E31: 0.225 | F31: 104 | G31: 0.15568862
E32: 0.25 | F32: 3 | G32: 0.21428571
E33: 0.28334 | F33: 0 | G33: 0
E34: 0.3 | F34: 508 | G34: 0.28603604
E35: Grand Total | F35: 952 | G35: 0.21794872

Sheet Master_Loan_Book
A1: customerid | B1: systemloanid | C1: loannumber | D1: approveddate | E1: creationdate | F1: loanamount | G1: totaldue | H1: termdays | I1: referredby | J1: good_bad_flag | K1: interestmarkup(%) | L1: repaymentstatusflag | M1: borrowervintagetier | N1: borrowerbank | O1: employmentstatus
A2: 8a2a81a74ce8c05d014cfb32a0da1049 | B2: 301994762 | C2: 12 | D2: 42941.349 | E2: 42941.307 | F2: 30000 | G2: 34500 | H2: 30 | J2: Good | K2: =(G2 - F2) / F2 -> 0.15 | L2: =IF(J2="bad", 1, 0) -> 0 | M2: =IF(C2=1, "1. First-Time Applicant", IF(C2<=3, "2. Early Repeat (2-3)", "3. High Velocity Loyalty (4+)")) -> 3. High Velocity Loyalty (4+) | N2: =IFERROR(INDEX(Demographics!F:F, MATCH(A2, Demographics!A:A, 0)), "Unspecified Bank") -> Diamond Bank | O2: =IFERROR(INDEX(Demographics!H:H, MATCH(A2, Demographics!A:A, 0)) & "", "Unknown Status") -> Permanent
A3: 8a85886e54beabf90154c0a29ae757c0 | B3: 301965204 | C3: 2 | D3: 42921.712 | E3: 42921.67 | F3: 15000 | G3: 17250 | H3: 30 | J3: Good | K3: =(G3 - F3) / F3 -> 0.15 | L3: =IF(J3="bad", 1, 0) -> 0 | M3: =IF(C3=1, "1. First-Time Applicant", IF(C3<=3, "2. Early Repeat (2-3)", "3. High Velocity Loyalty (4+)")) -> 2. Early Repeat (2-3) | N3: =IFERROR(INDEX(Demographics!F:F, MATCH(A3, Demographics!A:A, 0)), "Unspecified Bank") -> GT Bank | O3: =IFERROR(INDEX(Demographics!H:H, MATCH(A3, Demographics!A:A, 0)) & "", "Unknown Status") -> Permanent
A4: 8a8588f35438fe12015444567666018e | B4: 301966580 | C4: 7 | D4: 42922.62 | E4: 42922.578 | F4: 20000 | G4: 22250 | H4: 15 | J4: Good | K4: =(G4 - F4) / F4 -> 0.1125 | L4: =IF(J4="bad", 1, 0) -> 0 | M4: =IF(C4=1, "1. First-Time Applicant", IF(C4<=3, "2. Early Repeat (2-3)", "3. High Velocity Loyalty (4+)")) -> 3. High Velocity Loyalty (4+) | N4: =IFERROR(INDEX(Demographics!F:F, MATCH(A4, Demographics!A:A, 0)), "Unspecified Bank") -> EcoBank | O4: =IFERROR(INDEX(Demographics!H:H, MATCH(A4, Demographics!A:A, 0)) & "", "Unknown Status") -> Permanent
A5: 8a85890754145ace015429211b513e16 | B5: 301999343 | C5: 3 | D5: 42943.792 | E5: 42943.75 | F5: 10000 | G5: 11500 | H5: 15 | J5: Good | K5: =(G5 - F5) / F5 -> 0.15 | L5: =IF(J5="bad", 1, 0) -> 0 | M5: =IF(C5=1, "1. First-Time Applicant", IF(C5<=3, "2. Early Repeat (2-3)", "3. High Velocity Loyalty (4+)")) -> 2. Early Repeat (2-3) | N5: =IFERROR(INDEX(Demographics!F:F, MATCH(A5, Demographics!A:A, 0)), "Unspecified Bank") -> First Bank | O5: =IFERROR(INDEX(Demographics!H:H, MATCH(A5, Demographics!A:A, 0)) & "", "Unknown Status") -> Permanent
A6: 8a858970548359cc0154883481981866 | B6: 301962360 | C6: 9 | D6: 42919.988 | E6: 42919.946 | F6: 40000 | G6: 44000 | H6: 30 | J6: Good | K6: =(G6 - F6) / F6 -> 0.1 | L6: =IF(J6="bad", 1, 0) -> 0 | M6: =IF(C6=1, "1. First-Time Applicant", IF(C6<=3, "2. Early Repeat (2-3)", "3. High Velocity Loyalty (4+)")) -> 3. High Velocity Loyalty (4+) | N6: =IFERROR(INDEX(Demographics!F:F, MATCH(A6, Demographics!A:A, 0)), "Unspecified Bank") -> GT Bank | O6: =IFERROR(INDEX(Demographics!H:H, MATCH(A6, Demographics!A:A, 0)) & "", "Unknown Status") -> Permanent
A7: 8a8589f35451855401546b0738c42524 | B7: 301986516 | C7: 8 | D7: 42935.907 | E7: 42935.865 | F7: 30000 | G7: 39000 | H7: 60 | J7: Good | K7: =(G7 - F7) / F7 -> 0.3 | L7: =IF(J7="bad", 1, 0) -> 0 | M7: =IF(C7=1, "1. First-Time Applicant", IF(C7<=3, "2. Early Repeat (2-3)", "3. High Velocity Loyalty (4+)")) -> 3. High Velocity Loyalty (4+) | N7: =IFERROR(INDEX(Demographics!F:F, MATCH(A7, Demographics!A:A, 0)), "Unspecified Bank") -> Unspecified Bank | O7: =IFERROR(INDEX(Demographics!H:H, MATCH(A7, Demographics!A:A, 0)) & "", "Unknown Status") -> Unknown Status
A8: 8a858e095c59b91b015c5e5cea3719bc | B8: 301972027 | C8: 3 | D8: 42926.809 | E8: 42926.768 | F8: 10000 | G8: 13000 | H8: 30 | J8: Good | K8: =(G8 - F8) / F8 -> 0.3 | L8: =IF(J8="bad", 1, 0) -> 0 | M8: =IF(C8=1, "1. First-Time Applicant", IF(C8<=3, "2. Early Repeat (2-3)", "3. High Velocity Loyalty (4+)")) -> 2. Early Repeat (2-3) | N8: =IFERROR(INDEX(Demographics!F:F, MATCH(A8, Demographics!A:A, 0)), "Unspecified Bank") -> GT Bank | O8: =IFERROR(INDEX(Demographics!H:H, MATCH(A8, Demographics!A:A, 0)) & "", "Unknown Status") -> Permanent
A9: 8a858e1158dc4d830158f7bde4f47ea7 | B9: 301994428 | C9: 10 | D9: 42940.988 | E9: 42940.946 | F9: 30000 | G9: 34500 | H9: 30 | J9: Good | K9: =(G9 - F9) / F9 -> 0.15 | L9: =IF(J9="bad", 1, 0) -> 0 | M9: =IF(C9=1, "1. First-Time Applicant", IF(C9<=3, "2. Early Repeat (2-3)", "3. High Velocity Loyalty (4+)")) -> 3. High Velocity Loyalty (4+) | N9: =IFERROR(INDEX(Demographics!F:F, MATCH(A9, Demographics!A:A, 0)), "Unspecified Bank") -> First Bank | O9: =IFERROR(INDEX(Demographics!H:H, MATCH(A9, Demographics!A:A, 0)) & "", "Unknown Status")
A10: 8a858e185b4923b4015b4ae48d28646a | B10: 301996687 | C10: 4 | D10: 42942.454 | E10: 42942.412 | F10: 10000 | G10: 11500 | H10: 15 | J10: Good | K10: =(G10 - F10) / F10 -> 0.15 | L10: =IF(J10="bad", 1, 0) -> 0 | M10: =IF(C10=1, "1. First-Time Applicant", IF(C10<=3, "2. Early Repeat (2-3)", "3. High Velocity Loyalty (4+)")) -> 3. High Velocity Loyalty (4+) | N10: =IFERROR(INDEX(Demographics!F:F, MATCH(A10, Demographics!A:A, 0)), "Unspecified Bank") -> GT Bank | O10: =IFERROR(INDEX(Demographics!H:H, MATCH(A10, Demographics!A:A, 0)) & "", "Unknown Status") -> Permanent
A11: 8a858e1d5cd58f9e015ceda4bdb63673 | B11: 301981931 | C11: 2 | D11: 42933.575 | E11: 42933.534 | F11: 10000 | G11: 11500 | H11: 15 | J11: Good | K11: =(G11 - F11) / F11 -> 0.15 | L11: =IF(J11="bad", 1, 0) -> 0 | M11: =IF(C11=1, "1. First-Time Applicant", IF(C11<=3, "2. Early Repeat (2-3)", "3. High Velocity Loyalty (4+)")) -> 2. Early Repeat (2-3) | N11: =IFERROR(INDEX(Demographics!F:F, MATCH(A11, Demographics!A:A, 0)), "Unspecified Bank") -> Access Bank | O11: =IFERROR(INDEX(Demographics!H:H, MATCH(A11, Demographics!A:A, 0)) & "", "Unknown Status") -> Unemployed
A12: 8a858e245c214660015c2ba8187976f7 | B12: 301962365 | C12: 2 | D12: 42919.992 | E12: 42919.951 | F12: 10000 | G12: 13000 | H12: 30 | J12: Good | K12: =(G12 - F12) / F12 -> 0.3 | L12: =IF(J12="bad", 1, 0) -> 0 | M12: =IF(C12=1, "1. First-Time Applicant", IF(C12<=3, "2. Early Repeat (2-3)", "3. High Velocity Loyalty (4+)")) -> 2. Early Repeat (2-3) | N12: =IFERROR(INDEX(Demographics!F:F, MATCH(A12, Demographics!A:A, 0)), "Unspecified Bank") -> EcoBank | O12: =IFERROR(INDEX(Demographics!H:H, MATCH(A12, Demographics!A:A, 0)) & "", "Unknown Status") -> Permanent
A13: 8a858e345bd96da8015be6b9f8bc10c7 | B13: 301960371 | C13: 3 | D13: 42918.916 | E13: 42918.874 | F13: 10000 | G13: 13000 | H13: 30 | J13: Bad | K13: =(G13 - F13) / F13 -> 0.3 | L13: =IF(J13="bad", 1, 0) -> 1 | M13: =IF(C13=1, "1. First-Time Applicant", IF(C13<=3, "2. Early Repeat (2-3)", "3. High Velocity Loyalty (4+)")) -> 2. Early Repeat (2-3) | N13: =IFERROR(INDEX(Demographics!F:F, MATCH(A13, Demographics!A:A, 0)), "Unspecified Bank") -> GT Bank | O13: =IFERROR(INDEX(Demographics!H:H, MATCH(A13, Demographics!A:A, 0)) & "", "Unknown Status") -> Permanent
... A18: 8a858e645755e62201576b58e3522081 | B18: 301958834 | C18: 3 | D18: 42917.49 | E18: 42917.448 | F18: 10000 | G18: 11500 | H18: 15 | J18: Good | K18: =(G18 - F18) / F18 -> 0.15 | L18: =IF(J18="bad", 1, 0) -> 0 | M18: =IF(C18=1, "1. First-Time Applicant", IF(C18<=3, "2. Early Repeat (2-3)", "3. High Velocity Loyalty (4+)")) -> 2. Early Repeat (2-3) | N18: =IFERROR(INDEX(Demographics!F:F, MATCH(A18, Demographics!A:A, 0)), "Unspecified Bank") -> UBA | O18: =IFERROR(INDEX(Demographics!H:H, MATCH(A18, Demographics!A:A, 0)) & "", "Unknown Status") -> Permanent
A19: 8a858e6c5bd3fbff015bd408ac3e067a | B19: 301993535 | C19: 2 | D19: 42940.609 | E19: 42940.567 | F19: 10000 | G19: 11500 | H19: 15 | I19: 8a858ef458d4a52e0158d858eb5d6456 | J19: Bad | K19: =(G19 - F19) / F19 -> 0.15 | L19: =IF(J19="bad", 1, 0) -> 1 | M19: =IF(C19=1, "1. First-Time Applicant", IF(C19<=3, "2. Early Repeat (2-3)", "3. High Velocity Loyalty (4+)")) -> 2. Early Repeat (2-3) | N19: =IFERROR(INDEX(Demographics!F:F, MATCH(A19, Demographics!A:A, 0)), "Unspecified Bank") -> GT Bank | O19: =IFERROR(INDEX(Demographics!H:H, MATCH(A19, Demographics!A:A, 0)) & "", "Unknown Status")
A20: 8a858e705668e16701567f1523211e5a | B20: 301985106 | C20: 15 | D20: 42935.346 | E20: 42935.304 | F20: 40000 | G20: 44000 | H20: 30 | J20: Good | K20: =(G20 - F20) / F20 -> 0.1 | L20: =IF(J20="bad", 1, 0) -> 0 | M20: =IF(C20=1, "1. First-Time Applicant", IF(C20<=3, "2. Early Repeat (2-3)", "3. High Velocity Loyalty (4+)")) -> 3. High Velocity Loyalty (4+) | N20: =IFERROR(INDEX(Demographics!F:F, MATCH(A20, Demographics!A:A, 0)), "Unspecified Bank") -> Diamond Bank | O20: =IFERROR(INDEX(Demographics!H:H, MATCH(A20, Demographics!A:A, 0)) & "", "Unknown Status") -> Permanent
A21: 8a858e7d595026f8015951c0c4a03fae | B21: 301959458 | C21: 10 | D21: 42917.91 | E21: 42917.868 | F21: 30000 | G21: 34500 | H21: 30 | J21: Good | K21: =(G21 - F21) / F21 -> 0.15 | L21: =IF(J21="bad", 1, 0) -> 0 | M21: =IF(C21=1, "1. First-Time Applicant", IF(C21<=3, "2. Early Repeat (2-3)", "3. High Velocity Loyalty (4+)")) -> 3. High Velocity Loyalty (4+) | N21: =IFERROR(INDEX(Demographics!F:F, MATCH(A21, Demographics!A:A, 0)), "Unspecified Bank") -> Diamond Bank | O21: =IFERROR(INDEX(Demographics!H:H, MATCH(A21, Demographics!A:A, 0)) & "", "Unknown Status") -> Permanent
A22: 8a858e885c17687c015c19eead6338fd | B22: 301964283 | C22: 3 | D22: 42921.315 | E22: 42921.274 | F22: 10000 | G22: 13000 | H22: 30 | I22: 8a858ff85bd93919015bda56605652bd | J22: Good | K22: =(G22 - F22) / F22 -> 0.3 | L22: =IF(J22="bad", 1, 0) -> 0 | M22: =IF(C22=1, "1. First-Time Applicant", IF(C22<=3, "2. Early Repeat (2-3)", "3. High Velocity Loyalty (4+)")) -> 2. Early Repeat (2-3) | N22: =IFERROR(INDEX(Demographics!F:F, MATCH(A22, Demographics!A:A, 0)), "Unspecified Bank") -> GT Bank | O22: =IFERROR(INDEX(Demographics!H:H, MATCH(A22, Demographics!A:A, 0)) & "", "Unknown Status") -> Permanent
A23: 8a858e8f5d41c974015d4b7f31865627 | B23: 302003432 | C23: 2 | D23: 42946.56 | E23: 42946.518 | F23: 10000 | G23: 11500 | H23: 15 | I23: 8a858e495d1e235c015d30d5ddb42149 | J23: Bad | K23: =(G23 - F23) / F23 -> 0.15 | L23: =IF(J23="bad", 1, 0) -> 1 | M23: =IF(C23=1, "1. First-Time Applicant", IF(C23<=3, "2. Early Repeat (2-3)", "3. High Velocity Loyalty (4+)")) -> 2. Early Repeat (2-3) | N23: =IFERROR(INDEX(Demographics!F:F, MATCH(A23, Demographics!A:A, 0)), "Unspecified Bank") -> First Bank | O23: =IFERROR(INDEX(Demographics!H:H, MATCH(A23, Demographics!A:A, 0)) & "", "Unknown Status") -> Permanent
A24: 8a858e9b5a195041015a1a602a51519d | B24: 301976439 | C24: 7 | D24: 42929.735 | E24: 42929.693 | F24: 25000 | G24: 28750 | H24: 30 | J24: Good | K24: =(G24 - F24) / F24 -> 0.15 | L24: =IF(J24="bad", 1, 0) -> 0 | M24: =IF(C24=1, "1. First-Time Applicant", IF(C24<=3, "2. Early Repeat (2-3)", "3. High Velocity Loyalty (4+)")) -> 3. High Velocity Loyalty (4+) | N24: =IFERROR(INDEX(Demographics!F:F, MATCH(A24, Demographics!A:A, 0)), "Unspecified Bank") -> GT Bank | O24: =IFERROR(INDEX(Demographics!H:H, MATCH(A24, Demographics!A:A, 0)) & "", "Unknown Status")
A25: 8a858ea555d9e6020155f489c9b237f8 | B25: 301973446 | C25: 3 | D25: 42927.724 | E25: 42927.682 | F25: 10000 | G25: 13000 | H25: 30 | J25: Good | K25: =(G25 - F25) / F25 -> 0.3 | L25: =IF(J25="bad", 1, 0) -> 0 | M25: =IF(C25=1, "1. First-Time Applicant", IF(C25<=3, "2. Early Repeat (2-3)", "3. High Velocity Loyalty (4+)")) -> 2. Early Repeat (2-3) | N25: =IFERROR(INDEX(Demographics!F:F, MATCH(A25, Demographics!A:A, 0)), "Unspecified Bank") -> GT Bank | O25: =IFERROR(INDEX(Demographics!H:H, MATCH(A25, Demographics!A:A, 0)) & "", "Unknown Status") -> Permanent
A26: 8a858eb05d2d1297015d313b03581809 | B26: 301999087 | C26: 2 | D26: 42943.682 | E26: 42943.64 | F26: 10000 | G26: 13000 | H26: 30 | J26: Good | K26: =(G26 - F26) / F26 -> 0.3 | L26: =IF(J26="bad", 1, 0) -> 0 | M26: =IF(C26=1, "1. First-Time Applicant", IF(C26<=3, "2. Early Repeat (2-3)", "3. High Velocity Loyalty (4+)")) -> 2. Early Repeat (2-3) | N26: =IFERROR(INDEX(Demographics!F:F, MATCH(A26, Demographics!A:A, 0)), "Unspecified Bank") -> GT Bank | O26: =IFERROR(INDEX(Demographics!H:H, MATCH(A26, Demographics!A:A, 0)) & "", "Unknown Status") -> Permanent
A27: 8a858eb85c1be44c015c1c4b667d25ee | B27: 301963210 | C27: 3 | D27: 42920.579 | E27: 42920.537 | F27: 10000 | G27: 13000 | H27: 30 | J27: Good | K27: =(G27 - F27) / F27 -> 0.3 | L27: =IF(J27="bad", 1, 0) -> 0 | M27: =IF(C27=1, "1. First-Time Applicant", IF(C27<=3, "2. Early Repeat (2-3)", "3. High Velocity Loyalty (4+)")) -> 2. Early Repeat (2-3) | N27: =IFERROR(INDEX(Demographics!F:F, MATCH(A27, Demographics!A:A, 0)), "Unspecified Bank") -> GT Bank | O27: =IFERROR(INDEX(Demographics!H:H, MATCH(A27, Demographics!A:A, 0)) & "", "Unknown Status") -> Permanent
A28: 8a858ec75bfd77c4015c0d841520351c | B28: 301959286 | C28: 4 | D28: 42917.776 | E28: 42917.734 | F28: 20000 | G28: 24500 | H28: 30 | J28: Good | K28: =(G28 - F28) / F28 -> 0.225 | L28: =IF(J28="bad", 1, 0) -> 0 | M28: =IF(C28=1, "1. First-Time Applicant", IF(C28<=3, "2. Early Repeat (2-3)", "3. High Velocity Loyalty (4+)")) -> 3. High Velocity Loyalty (4+) | N28: =IFERROR(INDEX(Demographics!F:F, MATCH(A28, Demographics!A:A, 0)), "Unspecified Bank") -> Union Bank | O28: =IFERROR(INDEX(Demographics!H:H, MATCH(A28, Demographics!A:A, 0)) & "", "Unknown Status") -> Permanent
A29: 8a858ed35cc5ce51015cc60f40f522b4 | B29: 301981535 | C29: 2 | D29: 42933.44 | E29: 42933.398 | F29: 10000 | G29: 11500 | H29: 15 | I29: 8a858edc59ee87640159eeb9774f1aa7 | J29: Good | K29: =(G29 - F29) / F29 -> 0.15 | L29: =IF(J29="bad", 1, 0) -> 0 | M29: =IF(C29=1, "1. First-Time Applicant", IF(C29<=3, "2. Early Repeat (2-3)", "3. High Velocity Loyalty (4+)")) -> 2. Early Repeat (2-3) | N29: =IFERROR(INDEX(Demographics!F:F, MATCH(A29, Demographics!A:A, 0)), "Unspecified Bank") -> GT Bank | O29: =IFERROR(INDEX(Demographics!H:H, MATCH(A29, Demographics!A:A, 0)) & "", "Unknown Status") -> Permanent
A30: 8a858edb5ad79cc6015ad7c9b29415c8 | B30: 301981500 | C30: 5 | D30: 42933.428 | E30: 42933.386 | F30: 20000 | G30: 22250 | H30: 15 | J30: Good | K30: =(G30 - F30) / F30 -> 0.1125 | L30: =IF(J30="bad", 1, 0) -> 0 | M30: =IF(C30=1, "1. First-Time Applicant", IF(C30<=3, "2. Early Repeat (2-3)", "3. High Velocity Loyalty (4+)")) -> 3. High Velocity Loyalty (4+) | N30: =IFERROR(INDEX(Demographics!F:F, MATCH(A30, Demographics!A:A, 0)), "Unspecified Bank") -> GT Bank | O30: =IFERROR(INDEX(Demographics!H:H, MATCH(A30, Demographics!A:A, 0)) & "", "Unknown Status") -> Permanent
A31: 8a858ee55830c4b90158337542ab18a1 | B31: 301972649 | C31: 6 | D31: 42927.395 | E31: 42927.352 | F31: 10000 | G31: 13000 | H31: 30 | J31: Bad | K31: =(G31 - F31) / F31 -> 0.3 | L31: =IF(J31="bad", 1, 0) -> 1 | M31: =IF(C31=1, "1. First-Time Applicant", IF(C31<=3, "2. Early Repeat (2-3)", "3. High Velocity Loyalty (4+)")) -> 3. High Velocity Loyalty (4+) | N31: =IFERROR(INDEX(Demographics!F:F, MATCH(A31, Demographics!A:A, 0)), "Unspecified Bank") -> Unspecified Bank | O31: =IFERROR(INDEX(Demographics!H:H, MATCH(A31, Demographics!A:A, 0)) & "", "Unknown Status") -> Unknown Status
A32: 8a858eec5ca21dcb015ca2493dee1e2d | B32: 301966278 | C32: 2 | D32: 42922.486 | E32: 42922.444 | F32: 10000 | G32: 13000 | H32: 30 | J32: Good | K32: =(G32 - F32) / F32 -> 0.3 | L32: =IF(J32="bad", 1, 0) -> 0 | M32: =IF(C32=1, "1. First-Time Applicant", IF(C32<=3, "2. Early Repeat (2-3)", "3. High Velocity Loyalty (4+)")) -> 2. Early Repeat (2-3) | N32: =IFERROR(INDEX(Demographics!F:F, MATCH(A32, Demographics!A:A, 0)), "Unspecified Bank") -> UBA | O32: =IFERROR(INDEX(Demographics!H:H, MATCH(A32, Demographics!A:A, 0)) & "", "Unknown Status") -> Permanent
A33: 8a858ef75997d0180159a695b01e2c4c | B33: 301989547 | C33: 5 | D33: 42937.656 | E33: 42937.614 | F33: 20000 | G33: 24500 | H33: 30 | J33: Good | K33: =(G33 - F33) / F33 -> 0.225 | L33: =IF(J33="bad", 1, 0) -> 0 | M33: =IF(C33=1, "1. First-Time Applicant", IF(C33<=3, "2. Early Repeat (2-3)", "3. High Velocity Loyalty (4+)")) -> 3. High Velocity Loyalty (4+) | N33: =IFERROR(INDEX(Demographics!F:F, MATCH(A33, Demographics!A:A, 0)), "Unspecified Bank") -> First Bank | O33: =IFERROR(INDEX(Demographics!H:H, MATCH(A33, Demographics!A:A, 0)) & "", "Unknown Status")
A34: 8a858f03582604ff0158260fcc730548 | B34: 302001370 | C34: 10 | D34: 42944.898 | E34: 42944.857 | F34: 20000 | G34: 24500 | H34: 30 | J34: Good | K34: =(G34 - F34) / F34 -> 0.225 | L34: =IF(J34="bad", 1, 0) -> 0 | M34: =IF(C34=1, "1. First-Time Applicant", IF(C34<=3, "2. Early Repeat (2-3)", "3. High Velocity Loyalty (4+)")) -> 3. High Velocity Loyalty (4+) | N34: =IFERROR(INDEX(Demographics!F:F, MATCH(A34, Demographics!A:A, 0)), "Unspecified Bank") -> First Bank | O34: =IFERROR(INDEX(Demographics!H:H, MATCH(A34, Demographics!A:A, 0)) & "", "Unknown Status") -> Permanent
A35: 8a858f085b905684015b906e73a01478 | B35: 302000465 | C35: 4 | D35: 42944.522 | E35: 42944.479 | F35: 20000 | G35: 24500 | H35: 30 | J35: Good | K35: =(G35 - F35) / F35 -> 0.225 | L35: =IF(J35="bad", 1, 0) -> 0 | M35: =IF(C35=1, "1. First-Time Applicant", IF(C35<=3, "2. Early Repeat (2-3)", "3. High Velocity Loyalty (4+)")) -> 3. High Velocity Loyalty (4+) | N35: =IFERROR(INDEX(Demographics!F:F, MATCH(A35, Demographics!A:A, 0)), "Unspecified Bank") -> FCMB | O35: =IFERROR(INDEX(Demographics!H:H, MATCH(A35, Demographics!A:A, 0)) & "", "Unknown Status") -> Permanent
A36: 8a858f1955b1c4df0155cd14c5b478ed | B36: 302000569 | C36: 2 | D36: 42944.554 | E36: 42944.511 | F36: 10000 | G36: 13000 | H36: 30 | J36: Good | K36: =(G36 - F36) / F36 -> 0.3 | L36: =IF(J36="bad", 1, 0) -> 0 | M36: =IF(C36=1, "1. First-Time Applicant", IF(C36<=3, "2. Early Repeat (2-3)", "3. High Velocity Loyalty (4+)")) -> 2. Early Repeat (2-3) | N36: =IFERROR(INDEX(Demographics!F:F, MATCH(A36, Demographics!A:A, 0)), "Unspecified Bank") -> Unspecified Bank | O36: =IFERROR(INDEX(Demographics!H:H, MATCH(A36, Demographics!A:A, 0)) & "", "Unknown Status") -> Unknown Status
A37: 8a858f2656e154de0156e3a87cdc45fb | B37: 301982122 | C37: 5 | D37: 42933.644 | E37: 42933.602 | F37: 20000 | G37: 22250 | H37: 15 | J37: Good | K37: =(G37 - F37) / F37 -> 0.1125 | L37: =IF(J37="bad", 1, 0) -> 0 | M37: =IF(C37=1, "1. First-Time Applicant", IF(C37<=3, "2. Early Repeat (2-3)", "3. High Velocity Loyalty (4+)")) -> 3. High Velocity Loyalty (4+) | N37: =IFERROR(INDEX(Demographics!F:F, MATCH(A37, Demographics!A:A, 0)), "Unspecified Bank") -> UBA | O37: =IFERROR(INDEX(Demographics!H:H, MATCH(A37, Demographics!A:A, 0)) & "", "Unknown Status") -> Student
A38: 8a858f2e5c699f3a015c6cf27a036477 | B38: 301959225 | C38: 2 | D38: 42917.738 | E38: 42917.696 | F38: 10000 | G38: 13000 | H38: 30 | I38: 8a858fc55b2548dd015b286e452c678c | J38: Good | K38: =(G38 - F38) / F38 -> 0.3 | L38: =IF(J38="bad", 1, 0) -> 0 | M38: =IF(C38=1, "1. First-Time Applicant", IF(C38<=3, "2. Early Repeat (2-3)", "3. High Velocity Loyalty (4+)")) -> 2. Early Repeat (2-3) | N38: =IFERROR(INDEX(Demographics!F:F, MATCH(A38, Demographics!A:A, 0)), "Unspecified Bank") -> UBA | O38: =IFERROR(INDEX(Demographics!H:H, MATCH(A38, Demographics!A:A, 0)) & "", "Unknown Status") -> Permanent
A39: 8a858f335cd0c78e015cd435d7192800 | B39: 301984674 | C39: 2 | D39: 42934.897 | E39: 42934.856 | F39: 10000 | G39: 11500 | H39: 15 | J39: Good | K39: =(G39 - F39) / F39 -> 0.15 | L39: =IF(J39="bad", 1, 0) -> 0 | M39: =IF(C39=1, "1. First-Time Applicant", IF(C39<=3, "2. Early Repeat (2-3)", "3. High Velocity Loyalty (4+)")) -> 2. Early Repeat (2-3) | N39: =IFERROR(INDEX(Demographics!F:F, MATCH(A39, Demographics!A:A, 0)), "Unspecified Bank") -> GT Bank | O39: =IFERROR(INDEX(Demographics!H:H, MATCH(A39, Demographics!A:A, 0)) & "", "Unknown Status") -> Permanent
A40: 8a858f3d5add42e2015ae0ca6cb66b83 | B40: 301998400 | C40: 8 | D40: 42943.399 | E40: 42943.357 | F40: 30000 | G40: 34500 | H40: 30 | J40: Good | K40: =(G40 - F40) / F40 -> 0.15 | L40: =IF(J40="bad", 1, 0) -> 0 | M40: =IF(C40=1, "1. First-Time Applicant", IF(C40<=3, "2. Early Repeat (2-3)", "3. High Velocity Loyalty (4+)")) -> 3. High Velocity Loyalty (4+) | N40: =IFERROR(INDEX(Demographics!F:F, MATCH(A40, Demographics!A:A, 0)), "Unspecified Bank") -> Unspecified Bank | O40: =IFERROR(INDEX(Demographics!H:H, MATCH(A40, Demographics!A:A, 0)) & "", "Unknown Status") -> Unknown Status
A41: 8a858f4655ca643c0155cbc4e13945cc | B41: 301965090 | C41: 15 | D41: 42921.658 | E41: 42921.616 | F41: 40000 | G41: 44000 | H41: 30 | J41: Good | K41: =(G41 - F41) / F41 -> 0.1 | L41: =IF(J41="bad", 1, 0) -> 0 | M41: =IF(C41=1, "1. First-Time Applicant", IF(C41<=3, "2. Early Repeat (2-3)", "3. High Velocity Loyalty (4+)")) -> 3. High Velocity Loyalty (4+) | N41: =IFERROR(INDEX(Demographics!F:F, MATCH(A41, Demographics!A:A, 0)), "Unspecified Bank") -> GT Bank | O41: =IFERROR(INDEX(Demographics!H:H, MATCH(A41, Demographics!A:A, 0)) & "", "Unknown Status") -> Permanent
A42: 8a858f4f5511dca201551b73634170b6 | B42: 301997295 | C42: 4 | D42: 42942.677 | E42: 42942.636 | F42: 10000 | G42: 13000 | H42: 30 | J42: Good | K42: =(G42 - F42) / F42 -> 0.3 | L42: =IF(J42="bad", 1, 0) -> 0 | M42: =IF(C42=1, "1. First-Time Applicant", IF(C42<=3, "2. Early Repeat (2-3)", "3. High Velocity Loyalty (4+)")) -> 3. High Velocity Loyalty (4+) | N42: =IFERROR(INDEX(Demographics!F:F, MATCH(A42, Demographics!A:A, 0)), "Unspecified Bank") -> Unspecified Bank | O42: =IFERROR(INDEX(Demographics!H:H, MATCH(A42, Demographics!A:A, 0)) & "", "Unknown Status") -> Unknown Status
A43: 8a858f555cc65d60015cc72de106320c | B43: 301974694 | C43: 2 | D43: 42928.602 | E43: 42928.56 | F43: 10000 | G43: 13000 | H43: 30 | I43: 8a858e6c5c88d145015c89430ef61a5d | J43: Good | K43: =(G43 - F43) / F43 -> 0.3 | L43: =IF(J43="bad", 1, 0) -> 0 | M43: =IF(C43=1, "1. First-Time Applicant", IF(C43<=3, "2. Early Repeat (2-3)", "3. High Velocity Loyalty (4+)")) -> 2. Early Repeat (2-3) | N43: =IFERROR(INDEX(Demographics!F:F, MATCH(A43, Demographics!A:A, 0)), "Unspecified Bank") -> Unspecified Bank | O43: =IFERROR(INDEX(Demographics!H:H, MATCH(A43, Demographics!A:A, 0)) & "", "Unknown Status") -> Unknown Status
A44: 8a858f5e599783c0015997c56ef70ffa | B44: 302001086 | C44: 3 | D44: 42944.753 | E44: 42944.71 | F44: 10000 | G44: 11500 | H44: 15 | J44: Good | K44: =(G44 - F44) / F44 -> 0.15 | L44: =IF(J44="bad", 1, 0) -> 0 | M44: =IF(C44=1, "1. First-Time Applicant", IF(C44<=3, "2. Early Repeat (2-3)", "3. High Velocity Loyalty (4+)")) -> 2. Early Repeat (2-3) | N44: =IFERROR(INDEX(Demographics!F:F, MATCH(A44, Demographics!A:A, 0)), "Unspecified Bank") -> GT Bank | O44: =IFERROR(INDEX(Demographics!H:H, MATCH(A44, Demographics!A:A, 0)) & "", "Unknown Status")
A45: 8a858f60560bc43d01561d94abd91c48 | B45: 301991908 | C45: 4 | D45: 42939.578 | E45: 42939.536 | F45: 10000 | G45: 11500 | H45: 15 | J45: Good | K45: =(G45 - F45) / F45 -> 0.15 | L45: =IF(J45="bad", 1, 0) -> 0 | M45: =IF(C45=1, "1. First-Time Applicant", IF(C45<=3, "2. Early Repeat (2-3)", "3. High Velocity Loyalty (4+)")) -> 3. High Velocity Loyalty (4+) | N45: =IFERROR(INDEX(Demographics!F:F, MATCH(A45, Demographics!A:A, 0)), "Unspecified Bank") -> GT Bank | O45: =IFERROR(INDEX(Demographics!H:H, MATCH(A45, Demographics!A:A, 0)) & "", "Unknown Status") -> Permanent
A46: 8a858f6e5aa3c922015aa3d9cba10a74 | B46: 301983676 | C46: 5 | D46: 42934.503 | E46: 42934.461 | F46: 20000 | G46: 22250 | H46: 15 | J46: Good | K46: =(G46 - F46) / F46 -> 0.1125 | L46: =IF(J46="bad", 1, 0) -> 0 | M46: =IF(C46=1, "1. First-Time Applicant", IF(C46<=3, "2. Early Repeat (2-3)", "3. High Velocity Loyalty (4+)")) -> 3. High Velocity Loyalty (4+) | N46: =IFERROR(INDEX(Demographics!F:F, MATCH(A46, Demographics!A:A, 0)), "Unspecified Bank") -> Unspecified Bank | O46: =IFERROR(INDEX(Demographics!H:H, MATCH(A46, Demographics!A:A, 0)) & "", "Unknown Status") -> Unknown Status
A47: 8a858f785cea234f015cea434e0a09e6 | B47: 301974590 | C47: 2 | D47: 42928.556 | E47: 42928.515 | F47: 10000 | G47: 13000 | H47: 30 | I47: 8a858eba5c884d2a015c8bea59385157 | J47: Good | K47: =(G47 - F47) / F47 -> 0.3 | L47: =IF(J47="bad", 1, 0) -> 0 | M47: =IF(C47=1, "1. First-Time Applicant", IF(C47<=3, "2. Early Repeat (2-3)", "3. High Velocity Loyalty (4+)")) -> 2. Early Repeat (2-3) | N47: =IFERROR(INDEX(Demographics!F:F, MATCH(A47, Demographics!A:A, 0)), "Unspecified Bank") -> GT Bank | O47: =IFERROR(INDEX(Demographics!H:H, MATCH(A47, Demographics!A:A, 0)) & "", "Unknown Status") -> Permanent
A48: 8a858f7e564ad338015654d3a5c242a5 | B48: 301969110 | C48: 8 | D48: 42924.475 | E48: 42924.433 | F48: 30000 | G48: 34500 | H48: 30 | J48: Good | K48: =(G48 - F48) / F48 -> 0.15 | L48: =IF(J48="bad", 1, 0) -> 0 | M48: =IF(C48=1, "1. First-Time Applicant", IF(C48<=3, "2. Early Repeat (2-3)", "3. High Velocity Loyalty (4+)")) -> 3. High Velocity Loyalty (4+) | N48: =IFERROR(INDEX(Demographics!F:F, MATCH(A48, Demographics!A:A, 0)), "Unspecified Bank") -> GT Bank | O48: =IFERROR(INDEX(Demographics!H:H, MATCH(A48, Demographics!A:A, 0)) & "", "Unknown Status") -> Permanent
A49: 8a858f9158aff6a30158b5f2ff887585 | B49: 301985845 | C49: 9 | D49: 42935.622 | E49: 42935.58 | F49: 20000 | G49: 22250 | H49: 15 | J49: Good | K49: =(G49 - F49) / F49 -> 0.1125 | L49: =IF(J49="bad", 1, 0) -> 0 | M49: =IF(C49=1, "1. First-Time Applicant", IF(C49<=3, "2. Early Repeat (2-3)", "3. High Velocity Loyalty (4+)")) -> 3. High Velocity Loyalty (4+) | N49: =IFERROR(INDEX(Demographics!F:F, MATCH(A49, Demographics!A:A, 0)), "Unspecified Bank") -> GT Bank | O49: =IFERROR(INDEX(Demographics!H:H, MATCH(A49, Demographics!A:A, 0)) & "", "Unknown Status") -> Permanent
A50: 8a858f975c4582c4015c550ee4925686 | B50: 301998392 | C50: 3 | D50: 42943.396 | E50: 42943.355 | F50: 10000 | G50: 13000 | H50: 30 | J50: Good | K50: =(G50 - F50) / F50 -> 0.3 | L50: =IF(J50="bad", 1, 0) -> 0 | M50: =IF(C50=1, "1. First-Time Applicant", IF(C50<=3, "2. Early Repeat (2-3)", "3. High Velocity Loyalty (4+)")) -> 2. Early Repeat (2-3) | N50: =IFERROR(INDEX(Demographics!F:F, MATCH(A50, Demographics!A:A, 0)), "Unspecified Bank") -> Unspecified Bank | O50: =IFERROR(INDEX(Demographics!H:H, MATCH(A50, Demographics!A:A, 0)) & "", "Unknown Status") -> Unknown Status
A51: 8a858f995a4762a5015a4c25b0ea01c3 | B51: 301981230 | C51: 6 | D51: 42933.329 | E51: 42933.287 | F51: 20000 | G51: 24500 | H51: 30 | J51: Good | K51: =(G51 - F51) / F51 -> 0.225 | L51: =IF(J51="bad", 1, 0) -> 0 | M51: =IF(C51=1, "1. First-Time Applicant", IF(C51<=3, "2. Early Repeat (2-3)", "3. High Velocity Loyalty (4+)")) -> 3. High Velocity Loyalty (4+) | N51: =IFERROR(INDEX(Demographics!F:F, MATCH(A51, Demographics!A:A, 0)), "Unspecified Bank") -> Access Bank | O51: =IFERROR(INDEX(Demographics!H:H, MATCH(A51, Demographics!A:A, 0)) & "", "Unknown Status") -> Permanent
A52: 8a858fa45bd95e9a015be131cdec35a8 | B52: 301962952 | C52: 3 | D52: 42920.482 | E52: 42920.44 | F52: 10000 | G52: 13000 | H52: 30 | J52: Good | K52: =(G52 - F52) / F52 -> 0.3 | L52: =IF(J52="bad", 1, 0) -> 0 | M52: =IF(C52=1, "1. First-Time Applicant", IF(C52<=3, "2. Early Repeat (2-3)", "3. High Velocity Loyalty (4+)")) -> 2. Early Repeat (2-3) | N52: =IFERROR(INDEX(Demographics!F:F, MATCH(A52, Demographics!A:A, 0)), "Unspecified Bank") -> Zenith Bank | O52: =IFERROR(INDEX(Demographics!H:H, MATCH(A52, Demographics!A:A, 0)) & "", "Unknown Status") -> Permanent
A53: 8a858fae5b49223f015b499e1cf9485b | B53: 301982904 | C53: 4 | D53: 42934.003 | E53: 42933.96 | F53: 10000 | G53: 13000 | H53: 30 | J53: Bad | K53: =(G53 - F53) / F53 -> 0.3 | L53: =IF(J53="bad", 1, 0) -> 1 | M53: =IF(C53=1, "1. First-Time Applicant", IF(C53<=3, "2. Early Repeat (2-3)", "3. High Velocity Loyalty (4+)")) -> 3. High Velocity Loyalty (4+) | N53: =IFERROR(INDEX(Demographics!F:F, MATCH(A53, Demographics!A:A, 0)), "Unspecified Bank") -> GT Bank | O53: =IFERROR(INDEX(Demographics!H:H, MATCH(A53, Demographics!A:A, 0)) & "", "Unknown Status")
A54: 8a858fb15b34a708015b350c4a1a58d2 | B54: 301994303 | C54: 4 | D54: 42940.907 | E54: 42940.865 | F54: 20000 | G54: 24500 | H54: 30 | J54: Good | K54: =(G54 - F54) / F54 -> 0.225 | L54: =IF(J54="bad", 1, 0) -> 0 | M54: =IF(C54=1, "1. First-Time Applicant", IF(C54<=3, "2. Early Repeat (2-3)", "3. High Velocity Loyalty (4+)")) -> 3. High Velocity Loyalty (4+) | N54: =IFERROR(INDEX(Demographics!F:F, MATCH(A54, Demographics!A:A, 0)), "Unspecified Bank") -> UBA | O54: =IFERROR(INDEX(Demographics!H:H, MATCH(A54, Demographics!A:A, 0)) & "", "Unknown Status") -> Permanent
A55: 8a858fba5cd5feee015cda4f0fa423b4 | B55: 301991730 | C55: 2 | D55: 42939.46 | E55: 42939.418 | F55: 10000 | G55: 11500 | H55: 15 | J55: Good | K55: =(G55 - F55) / F55 -> 0.15 | L55: =IF(J55="bad", 1, 0) -> 0 | M55: =IF(C55=1, "1. First-Time Applicant", IF(C55<=3, "2. Early Repeat (2-3)", "3. High Velocity Loyalty (4+)")) -> 2. Early Repeat (2-3) | N55: =IFERROR(INDEX(Demographics!F:F, MATCH(A55, Demographics!A:A, 0)), "Unspecified Bank") -> Access Bank | O55: =IFERROR(INDEX(Demographics!H:H, MATCH(A55, Demographics!A:A, 0)) & "", "Unknown Status")
A56: 8a858fc55b2fde30015b30c9256b43fd | B56: 302001637 | C56: 5 | D56: 42945.263 | E56: 42945.22 | F56: 20000 | G56: 24500 | H56: 30 | J56: Good | K56: =(G56 - F56) / F56 -> 0.225 | L56: =IF(J56="bad", 1, 0) -> 0 | M56: =IF(C56=1, "1. First-Time Applicant", IF(C56<=3, "2. Early Repeat (2-3)", "3. High Velocity Loyalty (4+)")) -> 3. High Velocity Loyalty (4+) | N56: =IFERROR(INDEX(Demographics!F:F, MATCH(A56, Demographics!A:A, 0)), "Unspecified Bank") -> Unspecified Bank | O56: =IFERROR(INDEX(Demographics!H:H, MATCH(A56, Demographics!A:A, 0)) & "", "Unknown Status") -> Unknown Status
A57: 8a858fcb5ca240f7015ca64a71fa1951 | B57: 301960154 | C57: 2 | D57: 42918.741 | E57: 42918.699 | F57: 10000 | G57: 13000 | H57: 30 | J57: Good | K57: =(G57 - F57) / F57 -> 0.3 | L57: =IF(J57="bad", 1, 0) -> 0 | M57: =IF(C57=1, "1. First-Time Applicant", IF(C57<=3, "2. Early Repeat (2-3)", "3. High Velocity Loyalty (4+)")) -> 2. Early Repeat (2-3) | N57: =IFERROR(INDEX(Demographics!F:F, MATCH(A57, Demographics!A:A, 0)), "Unspecified Bank") -> First Bank | O57: =IFERROR(INDEX(Demographics!H:H, MATCH(A57, Demographics!A:A, 0)) & "", "Unknown Status") -> Permanent
A58: 8a858fd45a4260bc015a42ac9e89278d | B58: 301961250 | C58: 5 | D58: 42919.65 | E58: 42919.609 | F58: 20000 | G58: 24500 | H58: 30 | J58: Good | K58: =(G58 - F58) / F58 -> 0.225 | L58: =IF(J58="bad", 1, 0) -> 0 | M58: =IF(C58=1, "1. First-Time Applicant", IF(C58<=3, "2. Early Repeat (2-3)", "3. High Velocity Loyalty (4+)")) -> 3. High Velocity Loyalty (4+) | N58: =IFERROR(INDEX(Demographics!F:F, MATCH(A58, Demographics!A:A, 0)), "Unspecified Bank") -> Unspecified Bank | O58: =IFERROR(INDEX(Demographics!H:H, MATCH(A58, Demographics!A:A, 0)) & "", "Unknown Status") -> Unknown Status
A59: 8a858fd95c3b5bca015c3fcc0b374c3e | B59: 301968227 | C59: 2 | D59: 42923.679 | E59: 42923.637 | F59: 10000 | G59: 13000 | H59: 30 | J59: Good | K59: =(G59 - F59) / F59 -> 0.3 | L59: =IF(J59="bad", 1, 0) -> 0 | M59: =IF(C59=1, "1. First-Time Applicant", IF(C59<=3, "2. Early Repeat (2-3)", "3. High Velocity Loyalty (4+)")) -> 2. Early Repeat (2-3) | N59: =IFERROR(INDEX(Demographics!F:F, MATCH(A59, Demographics!A:A, 0)), "Unspecified Bank") -> UBA | O59: =IFERROR(INDEX(Demographics!H:H, MATCH(A59, Demographics!A:A, 0)) & "", "Unknown Status") -> Permanent
... A67: 8a858e1556321b940156548b9ca970a6 | B67: 301984218 | C67: 12 | D67: 42934.691 | E67: 42934.65 | F67: 40000 | G67: 48000 | H67: 60 | J67: Good | K67: =(G67 - F67) / F67 -> 0.2 | L67: =IF(J67="bad", 1, 0) -> 0 | M67: =IF(C67=1, "1. First-Time Applicant", IF(C67<=3, "2. Early Repeat (2-3)", "3. High Velocity Loyalty (4+)")) -> 3. High Velocity Loyalty (4+) | N67: =IFERROR(INDEX(Demographics!F:F, MATCH(A67, Demographics!A:A, 0)), "Unspecified Bank") -> Stanbic IBTC | O67: =IFERROR(INDEX(Demographics!H:H, MATCH(A67, Demographics!A:A, 0)) & "", "Unknown Status") -> Permanent
A68: 8a858e195b90e512015ba0eb4eed5ef5 | B68: 301964674 | C68: 5 | D68: 42921.483 | E68: 42921.441 | F68: 20000 | G68: 24500 | H68: 30 | I68: 8a858f9d5668e3f10156767e9a0f0188 | J68: Good | K68: =(G68 - F68) / F68 -> 0.225 | L68: =IF(J68="bad", 1, 0) -> 0 | M68: =IF(C68=1, "1. First-Time Applicant", IF(C68<=3, "2. Early Repeat (2-3)", "3. High Velocity Loyalty (4+)")) -> 3. High Velocity Loyalty (4+) | N68: =IFERROR(INDEX(Demographics!F:F, MATCH(A68, Demographics!A:A, 0)), "Unspecified Bank") -> Unspecified Bank | O68: =IFERROR(INDEX(Demographics!H:H, MATCH(A68, Demographics!A:A, 0)) & "", "Unknown Status") -> Unknown Status
A69: 8a858e205af28299015af50a799745c5 | B69: 301994002 | C69: 7 | D69: 42940.772 | E69: 42940.73 | F69: 30000 | G69: 39000 | H69: 60 | J69: Good | K69: =(G69 - F69) / F69 -> 0.3 | L69: =IF(J69="bad", 1, 0) -> 0 | M69: =IF(C69=1, "1. First-Time Applicant", IF(C69<=3, "2. Early Repeat (2-3)", "3. High Velocity Loyalty (4+)")) -> 3. High Velocity Loyalty (4+) | N69: =IFERROR(INDEX(Demographics!F:F, MATCH(A69, Demographics!A:A, 0)), "Unspecified Bank") -> UBA | O69: =IFERROR(INDEX(Demographics!H:H, MATCH(A69, Demographics!A:A, 0)) & "", "Unknown Status") -> Permanent
A70: 8a858e2e5bb57a37015bbe1b8d6d3830 | B70: 301964194 | C70: 3 | D70: 42921.251 | E70: 42921.209 | F70: 10000 | G70: 13000 | H70: 30 | J70: Good | K70: =(G70 - F70) / F70 -> 0.3 | L70: =IF(J70="bad", 1, 0) -> 0 | M70: =IF(C70=1, "1. First-Time Applicant", IF(C70<=3, "2. Early Repeat (2-3)", "3. High Velocity Loyalty (4+)")) -> 2. Early Repeat (2-3) | N70: =IFERROR(INDEX(Demographics!F:F, MATCH(A70, Demographics!A:A, 0)), "Unspecified Bank") -> Unspecified Bank | O70: =IFERROR(INDEX(Demographics!H:H, MATCH(A70, Demographics!A:A, 0)) & "", "Unknown Status") -> Unknown Status
A71: 8a858e3559080830015923412dd84294 | B71: 301972478 | C71: 10 | D71: 42927.303 | E71: 42927.26 | F71: 40000 | G71: 44000 | H71: 30 | J71: Good | K71: =(G71 - F71) / F71 -> 0.1 | L71: =IF(J71="bad", 1, 0) -> 0 | M71: =IF(C71=1, "1. First-Time Applicant", IF(C71<=3, "2. Early Repeat (2-3)", "3. High Velocity Loyalty (4+)")) -> 3. High Velocity Loyalty (4+) | N71: =IFERROR(INDEX(Demographics!F:F, MATCH(A71, Demographics!A:A, 0)), "Unspecified Bank") -> Unspecified Bank | O71: =IFERROR(INDEX(Demographics!H:H, MATCH(A71, Demographics!A:A, 0)) & "", "Unknown Status") -> Unknown Status
A72: 8a858e3e5b3ee747015b3f0409012b7f | B72: 301963059 | C72: 5 | D72: 42920.517 | E72: 42920.476 | F72: 30000 | G72: 39000 | H72: 60 | J72: Good | K72: =(G72 - F72) / F72 -> 0.3 | L72: =IF(J72="bad", 1, 0) -> 0 | M72: =IF(C72=1, "1. First-Time Applicant", IF(C72<=3, "2. Early Repeat (2-3)", "3. High Velocity Loyalty (4+)")) -> 3. High Velocity Loyalty (4+) | N72: =IFERROR(INDEX(Demographics!F:F, MATCH(A72, Demographics!A:A, 0)), "Unspecified Bank") -> Fidelity Bank | O72: =IFERROR(INDEX(Demographics!H:H, MATCH(A72, Demographics!A:A, 0)) & "", "Unknown Status") -> Permanent
A73: 8a858e4a5cac6f81015cad78a648389f | B73: 301988316 | C73: 2 | D73: 42936.873 | E73: 42936.831 | F73: 10000 | G73: 13000 | H73: 30 | I73: 8a858f645cac1a7e015cac2a1a5911f4 | J73: Good | K73: =(G73 - F73) / F73 -> 0.3 | L73: =IF(J73="bad", 1, 0) -> 0 | M73: =IF(C73=1, "1. First-Time Applicant", IF(C73<=3, "2. Early Repeat (2-3)", "3. High Velocity Loyalty (4+)")) -> 2. Early Repeat (2-3) | N73: =IFERROR(INDEX(Demographics!F:F, MATCH(A73, Demographics!A:A, 0)), "Unspecified Bank") -> Unspecified Bank | O73: =IFERROR(INDEX(Demographics!H:H, MATCH(A73, Demographics!A:A, 0)) & "", "Unknown Status") -> Unknown Status
A74: 8a858e575bf80f73015bfbc59df93401 | B74: 301967317 | C74: 3 | D74: 42923.091 | E74: 42923.049 | F74: 10000 | G74: 13000 | H74: 30 | I74: 8a858fad5bf85d5e015bf8efc79e33dd | J74: Good | K74: =(G74 - F74) / F74 -> 0.3 | L74: =IF(J74="bad", 1, 0) -> 0 | M74: =IF(C74=1, "1. First-Time Applicant", IF(C74<=3, "2. Early Repeat (2-3)", "3. High Velocity Loyalty (4+)")) -> 2. Early Repeat (2-3) | N74: =IFERROR(INDEX(Demographics!F:F, MATCH(A74, Demographics!A:A, 0)), "Unspecified Bank") -> Unspecified Bank | O74: =IFERROR(INDEX(Demographics!H:H, MATCH(A74, Demographics!A:A, 0)) & "", "Unknown Status") -> Unknown Status
A75: 8a858e625c8d993a015c95e7ced318df | B75: 301993647 | C75: 2 | D75: 42940.645 | E75: 42940.603 | F75: 10000 | G75: 13000 | H75: 30 | J75: Good | K75: =(G75 - F75) / F75 -> 0.3 | L75: =IF(J75="bad", 1, 0) -> 0 | M75: =IF(C75=1, "1. First-Time Applicant", IF(C75<=3, "2. Early Repeat (2-3)", "3. High Velocity Loyalty (4+)")) -> 2. Early Repeat (2-3) | N75: =IFERROR(INDEX(Demographics!F:F, MATCH(A75, Demographics!A:A, 0)), "Unspecified Bank") -> Access Bank | O75: =IFERROR(INDEX(Demographics!H:H, MATCH(A75, Demographics!A:A, 0)) & "", "Unknown Status") -> Permanent
A76: 8a858e655a047d1a015a12bb060936ff | B76: 301997062 | C76: 3 | D76: 42942.589 | E76: 42942.547 | F76: 10000 | G76: 13000 | H76: 30 | J76: Good | K76: =(G76 - F76) / F76 -> 0.3 | L76: =IF(J76="bad", 1, 0) -> 0 | M76: =IF(C76=1, "1. First-Time Applicant", IF(C76<=3, "2. Early Repeat (2-3)", "3. High Velocity Loyalty (4+)")) -> 2. Early Repeat (2-3) | N76: =IFERROR(INDEX(Demographics!F:F, MATCH(A76, Demographics!A:A, 0)), "Unspecified Bank") -> Unspecified Bank | O76: =IFERROR(INDEX(Demographics!H:H, MATCH(A76, Demographics!A:A, 0)) & "", "Unknown Status") -> Unknown Status
A77: 8a858e6e55c554c20155c6d8e2925c62 | B77: 301984086 | C77: 8 | D77: 42934.642 | E77: 42934.6 | F77: 10000 | G77: 13000 | H77: 30 | J77: Good | K77: =(G77 - F77) / F77 -> 0.3 | L77: =IF(J77="bad", 1, 0) -> 0 | M77: =IF(C77=1, "1. First-Time Applicant", IF(C77<=3, "2. Early Repeat (2-3)", "3. High Velocity Loyalty (4+)")) -> 3. High Velocity Loyalty (4+) | N77: =IFERROR(INDEX(Demographics!F:F, MATCH(A77, Demographics!A:A, 0)), "Unspecified Bank") -> GT Bank | O77: =IFERROR(INDEX(Demographics!H:H, MATCH(A77, Demographics!A:A, 0)) & "", "Unknown Status") -> Unemployed
A78: 8a858e785acd3412015acd7bdec42d4f | B78: 301965319 | C78: 6 | D78: 42921.759 | E78: 42921.717 | F78: 30000 | G78: 34500 | H78: 30 | J78: Good | K78: =(G78 - F78) / F78 -> 0.15 | L78: =IF(J78="bad", 1, 0) -> 0 | M78: =IF(C78=1, "1. First-Time Applicant", IF(C78<=3, "2. Early Repeat (2-3)", "3. High Velocity Loyalty (4+)")) -> 3. High Velocity Loyalty (4+) | N78: =IFERROR(INDEX(Demographics!F:F, MATCH(A78, Demographics!A:A, 0)), "Unspecified Bank") -> GT Bank | O78: =IFERROR(INDEX(Demographics!H:H, MATCH(A78, Demographics!A:A, 0)) & "", "Unknown Status") -> Permanent
A79: 8a858e875c63d395015c74bdfd343206 | B79: 302001775 | C79: 2 | D79: 42945.344 | E79: 42945.302 | F79: 10000 | G79: 13000 | H79: 30 | J79: Good | K79: =(G79 - F79) / F79 -> 0.3 | L79: =IF(J79="bad", 1, 0) -> 0 | M79: =IF(C79=1, "1. First-Time Applicant", IF(C79<=3, "2. Early Repeat (2-3)", "3. High Velocity Loyalty (4+)")) -> 2. Early Repeat (2-3) | N79: =IFERROR(INDEX(Demographics!F:F, MATCH(A79, Demographics!A:A, 0)), "Unspecified Bank") -> UBA | O79: =IFERROR(INDEX(Demographics!H:H, MATCH(A79, Demographics!A:A, 0)) & "", "Unknown Status") -> Student
A80: 8a858e8d56adbdae0156b30248fe3104 | B80: 301975923 | C80: 4 | D80: 42929.496 | E80: 42929.455 | F80: 20000 | G80: 24500 | H80: 30 | J80: Good | K80: =(G80 - F80) / F80 -> 0.225 | L80: =IF(J80="bad", 1, 0) -> 0 | M80: =IF(C80=1, "1. First-Time Applicant", IF(C80<=3, "2. Early Repeat (2-3)", "3. High Velocity Loyalty (4+)")) -> 3. High Velocity Loyalty (4+) | N80: =IFERROR(INDEX(Demographics!F:F, MATCH(A80, Demographics!A:A, 0)), "Unspecified Bank") -> Unspecified Bank | O80: =IFERROR(INDEX(Demographics!H:H, MATCH(A80, Demographics!A:A, 0)) & "", "Unknown Status") -> Unknown Status
A81: 8a858e985885ff6d01589211d7c01088 | B81: 301983843 | C81: 6 | D81: 42934.559 | E81: 42934.517 | F81: 20000 | G81: 24500 | H81: 30 | J81: Good | K81: =(G81 - F81) / F81 -> 0.225 | L81: =IF(J81="bad", 1, 0) -> 0 | M81: =IF(C81=1, "1. First-Time Applicant", IF(C81<=3, "2. Early Repeat (2-3)", "3. High Velocity Loyalty (4+)")) -> 3. High Velocity Loyalty (4+) | N81: =IFERROR(INDEX(Demographics!F:F, MATCH(A81, Demographics!A:A, 0)), "Unspecified Bank") -> GT Bank | O81: =IFERROR(INDEX(Demographics!H:H, MATCH(A81, Demographics!A:A, 0)) & "", "Unknown Status") -> Permanent
A82: 8a858ea15ca2565c015ca6ed24977b5e | B82: 301976588 | C82: 2 | D82: 42929.823 | E82: 42929.781 | F82: 10000 | G82: 13000 | H82: 30 | J82: Good | K82: =(G82 - F82) / F82 -> 0.3 | L82: =IF(J82="bad", 1, 0) -> 0 | M82: =IF(C82=1, "1. First-Time Applicant", IF(C82<=3, "2. Early Repeat (2-3)", "3. High Velocity Loyalty (4+)")) -> 2. Early Repeat (2-3) | N82: =IFERROR(INDEX(Demographics!F:F, MATCH(A82, Demographics!A:A, 0)), "Unspecified Bank") -> UBA | O82: =IFERROR(INDEX(Demographics!H:H, MATCH(A82, Demographics!A:A, 0)) & "", "Unknown Status") -> Permanent
A83: 8a858eaa55a0b8ae0155bab849c616a1 | B83: 301984604 | C83: 2 | D83: 42934.87 | E83: 42934.828 | F83: 10000 | G83: 13000 | H83: 30 | J83: Good | K83: =(G83 - F83) / F83 -> 0.3 | L83: =IF(J83="bad", 1, 0) -> 0 | M83: =IF(C83=1, "1. First-Time Applicant", IF(C83<=3, "2. Early Repeat (2-3)", "3. High Velocity Loyalty (4+)")) -> 2. Early Repeat (2-3) | N83: =IFERROR(INDEX(Demographics!F:F, MATCH(A83, Demographics!A:A, 0)), "Unspecified Bank") -> Diamond Bank | O83: =IFERROR(INDEX(Demographics!H:H, MATCH(A83, Demographics!A:A, 0)) & "", "Unknown Status") -> Permanent
A84: 8a858eb4596ff919015974a667560a89 | B84: 301968410 | C84: 8 | D84: 42923.782 | E84: 42923.74 | F84: 30000 | G84: 34500 | H84: 30 | J84: Good | K84: =(G84 - F84) / F84 -> 0.15 | L84: =IF(J84="bad", 1, 0) -> 0 | M84: =IF(C84=1, "1. First-Time Applicant", IF(C84<=3, "2. Early Repeat (2-3)", "3. High Velocity Loyalty (4+)")) -> 3. High Velocity Loyalty (4+) | N84: =IFERROR(INDEX(Demographics!F:F, MATCH(A84, Demographics!A:A, 0)), "Unspecified Bank") -> First Bank | O84: =IFERROR(INDEX(Demographics!H:H, MATCH(A84, Demographics!A:A, 0)) & "", "Unknown Status") -> Permanent
A85: 8a858ec55b441639015b444e78b7361f | B85: 301979821 | C85: 4 | D85: 42931.964 | E85: 42931.922 | F85: 10000 | G85: 11125 | H85: 15 | J85: Good | K85: =(G85 - F85) / F85 -> 0.1125 | L85: =IF(J85="bad", 1, 0) -> 0 | M85: =IF(C85=1, "1. First-Time Applicant", IF(C85<=3, "2. Early Repeat (2-3)", "3. High Velocity Loyalty (4+)")) -> 3. High Velocity Loyalty (4+) | N85: =IFERROR(INDEX(Demographics!F:F, MATCH(A85, Demographics!A:A, 0)), "Unspecified Bank") -> Unspecified Bank | O85: =IFERROR(INDEX(Demographics!H:H, MATCH(A85, Demographics!A:A, 0)) & "", "Unknown Status") -> Unknown Status
A86: 8a858ece5b0142e3015b0a3a7f183339 | B86: 302001189 | C86: 5 | D86: 42944.801 | E86: 42944.76 | F86: 20000 | G86: 24500 | H86: 30 | J86: Good | K86: =(G86 - F86) / F86 -> 0.225 | L86: =IF(J86="bad", 1, 0) -> 0 | M86: =IF(C86=1, "1. First-Time Applicant", IF(C86<=3, "2. Early Repeat (2-3)", "3. High Velocity Loyalty (4+)")) -> 3. High Velocity Loyalty (4+) | N86: =IFERROR(INDEX(Demographics!F:F, MATCH(A86, Demographics!A:A, 0)), "Unspecified Bank") -> Unspecified Bank | O86: =IFERROR(INDEX(Demographics!H:H, MATCH(A86, Demographics!A:A, 0)) & "", "Unknown Status") -> Unknown Status
... A94: 8a858f1f587161850158742ebbce53d8 | B94: 301974331 | C94: 9 | D94: 42928.442 | E94: 42928.4 | F94: 30000 | G94: 34500 | H94: 30 | J94: Good | K94: =(G94 - F94) / F94 -> 0.15 | L94: =IF(J94="bad", 1, 0) -> 0 | M94: =IF(C94=1, "1. First-Time Applicant", IF(C94<=3, "2. Early Repeat (2-3)", "3. High Velocity Loyalty (4+)")) -> 3. High Velocity Loyalty (4+) | N94: =IFERROR(INDEX(Demographics!F:F, MATCH(A94, Demographics!A:A, 0)), "Unspecified Bank") -> GT Bank | O94: =IFERROR(INDEX(Demographics!H:H, MATCH(A94, Demographics!A:A, 0)) & "", "Unknown Status") -> Permanent
A95: 8a858f275c451af5015c49a2c43b5fb2 | B95: 301980592 | C95: 2 | D95: 42932.705 | E95: 42932.663 | F95: 10000 | G95: 13000 | H95: 30 | I95: 8a858e725c3ae262015c45243caa4f4d | J95: Good | K95: =(G95 - F95) / F95 -> 0.3 | L95: =IF(J95="bad", 1, 0) -> 0 | M95: =IF(C95=1, "1. First-Time Applicant", IF(C95<=3, "2. Early Repeat (2-3)", "3. High Velocity Loyalty (4+)")) -> 2. Early Repeat (2-3) | N95: =IFERROR(INDEX(Demographics!F:F, MATCH(A95, Demographics!A:A, 0)), "Unspecified Bank") -> Sterling Bank | O95: =IFERROR(INDEX(Demographics!H:H, MATCH(A95, Demographics!A:A, 0)) & "", "Unknown Status") -> Permanent
A96: 8a858f305cb1ec4e015cb215f0500a8d | B96: 301978868 | C96: 2 | D96: 42931.401 | E96: 42931.359 | F96: 10000 | G96: 13000 | H96: 30 | I96: 8a858eda5c8863ff015c8b96e5fd74d0 | J96: Good | K96: =(G96 - F96) / F96 -> 0.3 | L96: =IF(J96="bad", 1, 0) -> 0 | M96: =IF(C96=1, "1. First-Time Applicant", IF(C96<=3, "2. Early Repeat (2-3)", "3. High Velocity Loyalty (4+)")) -> 2. Early Repeat (2-3) | N96: =IFERROR(INDEX(Demographics!F:F, MATCH(A96, Demographics!A:A, 0)), "Unspecified Bank") -> Access Bank | O96: =IFERROR(INDEX(Demographics!H:H, MATCH(A96, Demographics!A:A, 0)) & "", "Unknown Status") -> Permanent
A97: 8a858f375cef1cbc015ceff67d505f59 | B97: 302001119 | C97: 2 | D97: 42944.766 | E97: 42944.724 | F97: 10000 | G97: 13000 | H97: 30 | J97: Good | K97: =(G97 - F97) / F97 -> 0.3 | L97: =IF(J97="bad", 1, 0) -> 0 | M97: =IF(C97=1, "1. First-Time Applicant", IF(C97<=3, "2. Early Repeat (2-3)", "3. High Velocity Loyalty (4+)")) -> 2. Early Repeat (2-3) | N97: =IFERROR(INDEX(Demographics!F:F, MATCH(A97, Demographics!A:A, 0)), "Unspecified Bank") -> Zenith Bank | O97: =IFERROR(INDEX(Demographics!H:H, MATCH(A97, Demographics!A:A, 0)) & "", "Unknown Status")
A98: 8a858f425b85835d015b85bfe40538db | B98: 301966525 | C98: 2 | D98: 42922.596 | E98: 42922.554 | F98: 10000 | G98: 13000 | H98: 30 | J98: Good | K98: =(G98 - F98) / F98 -> 0.3 | L98: =IF(J98="bad", 1, 0) -> 0 | M98: =IF(C98=1, "1. First-Time Applicant", IF(C98<=3, "2. Early Repeat (2-3)", "3. High Velocity Loyalty (4+)")) -> 2. Early Repeat (2-3) | N98: =IFERROR(INDEX(Demographics!F:F, MATCH(A98, Demographics!A:A, 0)), "Unspecified Bank") -> Access Bank | O98: =IFERROR(INDEX(Demographics!H:H, MATCH(A98, Demographics!A:A, 0)) & "", "Unknown Status") -> Permanent
A99: 8a858f495c5973ce015c59c5f099417c | B99: 301994809 | C99: 3 | D99: 42941.369 | E99: 42941.328 | F99: 10000 | G99: 13000 | H99: 30 | J99: Good | K99: =(G99 - F99) / F99 -> 0.3 | L99: =IF(J99="bad", 1, 0) -> 0 | M99: =IF(C99=1, "1. First-Time Applicant", IF(C99<=3, "2. Early Repeat (2-3)", "3. High Velocity Loyalty (4+)")) -> 2. Early Repeat (2-3) | N99: =IFERROR(INDEX(Demographics!F:F, MATCH(A99, Demographics!A:A, 0)), "Unspecified Bank") -> Skye Bank | O99: =IFERROR(INDEX(Demographics!H:H, MATCH(A99, Demographics!A:A, 0)) & "", "Unknown Status") -> Permanent
A100: 8a858f54589736f401589857085e3b5b | B100: 301981912 | C100: 9 | D100: 42933.57 | E100: 42933.527 | F100: 40000 | G100: 44000 | H100: 30 | J100: Good | K100: =(G100 - F100) / F100 -> 0.1 | L100: =IF(J100="bad", 1, 0) -> 0 | M100: =IF(C100=1, "1. First-Time Applicant", IF(C100<=3, "2. Early Repeat (2-3)", "3. High Velocity Loyalty (4+)")) -> 3. High Velocity Loyalty (4+) | N100: =IFERROR(INDEX(Demographics!F:F, MATCH(A100, Demographics!A:A, 0)), "Unspecified Bank") -> Access Bank | O100: =IFERROR(INDEX(Demographics!H:H, MATCH(A100, Demographics!A:A, 0)) & "", "Unknown Status") -> Student
A101: 8a858f585bfd6341015c03694f85158f | B101: 301974102 | C101: 4 | D101: 42928.33 | E101: 42928.289 | F101: 10000 | G101: 11500 | H101: 15 | J101: Good | K101: =(G101 - F101) / F101 -> 0.15 | L101: =IF(J101="bad", 1, 0) -> 0 | M101: =IF(C101=1, "1. First-Time Applicant", IF(C101<=3, "2. Early Repeat (2-3)", "3. High Velocity Loyalty (4+)")) -> 3. High Velocity Loyalty (4+) | N101: =IFERROR(INDEX(Demographics!F:F, MATCH(A101, Demographics!A:A, 0)), "Unspecified Bank") -> Access Bank | O101: =IFERROR(INDEX(Demographics!H:H, MATCH(A101, Demographics!A:A, 0)) & "", "Unknown Status") -> Permanent
A102: 8a858f5e5cf45779015cf47ed8db1872 | B102: 302002546 | C102: 2 | D102: 42945.747 | E102: 42945.705 | F102: 10000 | G102: 13000 | H102: 30 | I102: 8a858ed75732b681015744c9dee21aae | J102: Good | K102: =(G102 - F102) / F102 -> 0.3 | L102: =IF(J102="bad", 1, 0) -> 0 | M102: =IF(C102=1, "1. First-Time Applicant", IF(C102<=3, "2. Early Repeat (2-3)", "3. High Velocity Loyalty (4+)")) -> 2. Early Repeat (2-3) | N102: =IFERROR(INDEX(Demographics!F:F, MATCH(A102, Demographics!A:A, 0)), "Unspecified Bank") -> GT Bank | O102: =IFERROR(INDEX(Demographics!H:H, MATCH(A102, Demographics!A:A, 0)) & "", "Unknown Status") -> Permanent
A103: 8a858f665c45930d015c54a24fdc1f6c | B103: 301969912 | C103: 2 | D103: 42925.303 | E103: 42925.262 | F103: 10000 | G103: 11500 | H103: 15 | J103: Good | K103: =(G103 - F103) / F103 -> 0.15 | L103: =IF(J103="bad", 1, 0) -> 0 | M103: =IF(C103=1, "1. First-Time Applicant", IF(C103<=3, "2. Early Repeat (2-3)", "3. High Velocity Loyalty (4+)")) -> 2. Early Repeat (2-3) | N103: =IFERROR(INDEX(Demographics!F:F, MATCH(A103, Demographics!A:A, 0)), "Unspecified Bank") -> Diamond Bank | O103: =IFERROR(INDEX(Demographics!H:H, MATCH(A103, Demographics!A:A, 0)) & "", "Unknown Status") -> Permanent
A104: 8a858f6f5b3f095b015b4083532532a0 | B104: 301990087 | C104: 2 | D104: 42937.919 | E104: 42937.878 | F104: 10000 | G104: 13000 | H104: 30 | J104: Good | K104: =(G104 - F104) / F104 -> 0.3 | L104: =IF(J104="bad", 1, 0) -> 0 | M104: =IF(C104=1, "1. First-Time Applicant", IF(C104<=3, "2. Early Repeat (2-3)", "3. High Velocity Loyalty (4+)")) -> 2. Early Repeat (2-3) | N104: =IFERROR(INDEX(Demographics!F:F, MATCH(A104, Demographics!A:A, 0)), "Unspecified Bank") -> Access Bank | O104: =IFERROR(INDEX(Demographics!H:H, MATCH(A104, Demographics!A:A, 0)) & "", "Unknown Status") -> Permanent
A105: 8a858f7a5ca22d3c015ca24d01461879 | B105: 301973351 | C105: 2 | D105: 42927.686 | E105: 42927.644 | F105: 10000 | G105: 13000 | H105: 30 | J105: Good | K105: =(G105 - F105) / F105 -> 0.3 | L105: =IF(J105="bad", 1, 0) -> 0 | M105: =IF(C105=1, "1. First-Time Applicant", IF(C105<=3, "2. Early Repeat (2-3)", "3. High Velocity Loyalty (4+)")) -> 2. Early Repeat (2-3) | N105: =IFERROR(INDEX(Demographics!F:F, MATCH(A105, Demographics!A:A, 0)), "Unspecified Bank") -> GT Bank | O105: =IFERROR(INDEX(Demographics!H:H, MATCH(A105, Demographics!A:A, 0)) & "", "Unknown Status") -> Unemployed
A106: 8a858f8d5cc56f9a015cc57e769908ac | B106: 301989000 | C106: 2 | D106: 42937.434 | E106: 42937.393 | F106: 10000 | G106: 13000 | H106: 30 | J106: Bad | K106: =(G106 - F106) / F106 -> 0.3 | L106: =IF(J106="bad", 1, 0) -> 1 | M106: =IF(C106=1, "1. First-Time Applicant", IF(C106<=3, "2. Early Repeat (2-3)", "3. High Velocity Loyalty (4+)")) -> 2. Early Repeat (2-3) | N106: =IFERROR(INDEX(Demographics!F:F, MATCH(A106, Demographics!A:A, 0)), "Unspecified Bank") -> Access Bank | O106: =IFERROR(INDEX(Demographics!H:H, MATCH(A106, Demographics!A:A, 0)) & "", "Unknown Status") -> Permanent
A107: 8a858f965bb63a25015bc22b915e62f1 | B107: 301985658 | C107: 5 | D107: 42935.555 | E107: 42935.513 | F107: 20000 | G107: 22250 | H107: 15 | J107: Good | K107: =(G107 - F107) / F107 -> 0.1125 | L107: =IF(J107="bad", 1, 0) -> 0 | M107: =IF(C107=1, "1. First-Time Applicant", IF(C107<=3, "2. Early Repeat (2-3)", "3. High Velocity Loyalty (4+)")) -> 3. High Velocity Loyalty (4+) | N107: =IFERROR(INDEX(Demographics!F:F, MATCH(A107, Demographics!A:A, 0)), "Unspecified Bank") -> UBA | O107: =IFERROR(INDEX(Demographics!H:H, MATCH(A107, Demographics!A:A, 0)) & "", "Unknown Status") -> Permanent
A108: 8a858f985b80ab2c015b81098b8f2c2e | B108: 301983234 | C108: 4 | D108: 42934.359 | E108: 42934.316 | F108: 20000 | G108: 24500 | H108: 30 | J108: Good | K108: =(G108 - F108) / F108 -> 0.225 | L108: =IF(J108="bad", 1, 0) -> 0 | M108: =IF(C108=1, "1. First-Time Applicant", IF(C108<=3, "2. Early Repeat (2-3)", "3. High Velocity Loyalty (4+)")) -> 3. High Velocity Loyalty (4+) | N108: =IFERROR(INDEX(Demographics!F:F, MATCH(A108, Demographics!A:A, 0)), "Unspecified Bank") -> Unspecified Bank | O108: =IFERROR(INDEX(Demographics!H:H, MATCH(A108, Demographics!A:A, 0)) & "", "Unknown Status") -> Unknown Status
A109: 8a858fa15c8ceaaa015c8d79c65f4f86 | B109: 301978213 | C109: 2 | D109: 42930.798 | E109: 42930.756 | F109: 10000 | G109: 13000 | H109: 30 | I109: 8a858e135c7e2eec015c813211a96674 | J109: Good | K109: =(G109 - F109) / F109 -> 0.3 | L109: =IF(J109="bad", 1, 0) -> 0 | M109: =IF(C109=1, "1. First-Time Applicant", IF(C109<=3, "2. Early Repeat (2-3)", "3. High Velocity Loyalty (4+)")) -> 2. Early Repeat (2-3) | N109: =IFERROR(INDEX(Demographics!F:F, MATCH(A109, Demographics!A:A, 0)), "Unspecified Bank") -> GT Bank | O109: =IFERROR(INDEX(Demographics!H:H, MATCH(A109, Demographics!A:A, 0)) & "", "Unknown Status") -> Permanent
A110: 8a858fa95b631878015b6401c15973f3 | B110: 301967211 | C110: 3 | D110: 42922.944 | E110: 42922.902 | F110: 10000 | G110: 11500 | H110: 15 | J110: Bad | K110: =(G110 - F110) / F110 -> 0.15 | L110: =IF(J110="bad", 1, 0) -> 1 | M110: =IF(C110=1, "1. First-Time Applicant", IF(C110<=3, "2. Early Repeat (2-3)", "3. High Velocity Loyalty (4+)")) -> 2. Early Repeat (2-3) | N110: =IFERROR(INDEX(Demographics!F:F, MATCH(A110, Demographics!A:A, 0)), "Unspecified Bank") -> Unspecified Bank | O110: =IFERROR(INDEX(Demographics!H:H, MATCH(A110, Demographics!A:A, 0)) & "", "Unknown Status") -> Unknown Status
A111: 8a858faf56b7821c0156b93cd62a6275 | B111: 301960745 | C111: 9 | D111: 42919.415 | E111: 42919.373 | F111: 40000 | G111: 48000 | H111: 60 | J111: Good | K111: =(G111 - F111) / F111 -> 0.2 | L111: =IF(J111="bad", 1, 0) -> 0 | M111: =IF(C111=1, "1. First-Time Applicant", IF(C111<=3, "2. Early Repeat (2-3)", "3. High Velocity Loyalty (4+)")) -> 3. High Velocity Loyalty (4+) | N111: =IFERROR(INDEX(Demographics!F:F, MATCH(A111, Demographics!A:A, 0)), "Unspecified Bank") -> Stanbic IBTC | O111: =IFERROR(INDEX(Demographics!H:H, MATCH(A111, Demographics!A:A, 0)) & "", "Unknown Status") -> Permanent
A112: 8a858fb45b3eef19015b3fa969390cd3 | B112: 301989976 | C112: 4 | D112: 42937.846 | E112: 42937.804 | F112: 20000 | G112: 22250 | H112: 15 | J112: Good | K112: =(G112 - F112) / F112 -> 0.1125 | L112: =IF(J112="bad", 1, 0) -> 0 | M112: =IF(C112=1, "1. First-Time Applicant", IF(C112<=3, "2. Early Repeat (2-3)", "3. High Velocity Loyalty (4+)")) -> 3. High Velocity Loyalty (4+) | N112: =IFERROR(INDEX(Demographics!F:F, MATCH(A112, Demographics!A:A, 0)), "Unspecified Bank") -> GT Bank | O112: =IFERROR(INDEX(Demographics!H:H, MATCH(A112, Demographics!A:A, 0)) & "", "Unknown Status") -> Permanent
A113: 8a858fbd5cd6054a015ce82aa3914088 | B113: 302003004 | C113: 2 | D113: 42946.233 | E113: 42946.191 | F113: 10000 | G113: 13000 | H113: 30 | J113: Good | K113: =(G113 - F113) / F113 -> 0.3 | L113: =IF(J113="bad", 1, 0) -> 0 | M113: =IF(C113=1, "1. First-Time Applicant", IF(C113<=3, "2. Early Repeat (2-3)", "3. High Velocity Loyalty (4+)")) -> 2. Early Repeat (2-3) | N113: =IFERROR(INDEX(Demographics!F:F, MATCH(A113, Demographics!A:A, 0)), "Unspecified Bank") -> Unspecified Bank | O113: =IFERROR(INDEX(Demographics!H:H, MATCH(A113, Demographics!A:A, 0)) & "", "Unknown Status") -> Unknown Status
A114: 8a858fca5c830943015c835e839e33a5 | B114: 301972727 | C114: 2 | D114: 42927.431 | E114: 42927.389 | F114: 10000 | G114: 11500 | H114: 15 | I114: 8a858ff25c8250c1015c82907bc62b42 | J114: Good | K114: =(G114 - F114) / F114 -> 0.15 | L114: =IF(J114="bad", 1, 0) -> 0 | M114: =IF(C114=1, "1. First-Time Applicant", IF(C114<=3, "2. Early Repeat (2-3)", "3. High Velocity Loyalty (4+)")) -> 2. Early Repeat (2-3) | N114: =IFERROR(INDEX(Demographics!F:F, MATCH(A114, Demographics!A:A, 0)), "Unspecified Bank") -> Access Bank | O114: =IFERROR(INDEX(Demographics!H:H, MATCH(A114, Demographics!A:A, 0)) & "", "Unknown Status")
A115: 8a858fcf5591c5cf015597c298cb15d9 | B115: 301982812 | C115: 2 | D115: 42933.938 | E115: 42933.896 | F115: 10000 | G115: 13000 | H115: 30 | J115: Good | K115: =(G115 - F115) / F115 -> 0.3 | L115: =IF(J115="bad", 1, 0) -> 0 | M115: =IF(C115=1, "1. First-Time Applicant", IF(C115<=3, "2. Early Repeat (2-3)", "3. High Velocity Loyalty (4+)")) -> 2. Early Repeat (2-3) | N115: =IFERROR(INDEX(Demographics!F:F, MATCH(A115, Demographics!A:A, 0)), "Unspecified Bank") -> Unspecified Bank | O115: =IFERROR(INDEX(Demographics!H:H, MATCH(A115, Demographics!A:A, 0)) & "", "Unknown Status") -> Unknown Status
A116: 8a858fd55c45ba15015c4f06ea176506 | B116: 301991520 | C116: 3 | D116: 42939.309 | E116: 42939.267 | F116: 10000 | G116: 11500 | H116: 15 | I116: 8a858e3a5bed83ab015bedad8d191c74 | J116: Good | K116: =(G116 - F116) / F116 -> 0.15 | L116: =IF(J116="bad", 1, 0) -> 0 | M116: =IF(C116=1, "1. First-Time Applicant", IF(C116<=3, "2. Early Repeat (2-3)", "3. High Velocity Loyalty (4+)")) -> 2. Early Repeat (2-3) | N116: =IFERROR(INDEX(Demographics!F:F, MATCH(A116, Demographics!A:A, 0)), "Unspecified Bank") -> Access Bank | O116: =IFERROR(INDEX(Demographics!H:H, MATCH(A116, Demographics!A:A, 0)) & "", "Unknown Status") -> Permanent
A117: 8a858fdf5bf85f71015bfc1f51f9690a | B117: 301978816 | C117: 2 | D117: 42931.37 | E117: 42931.329 | F117: 10000 | G117: 13000 | H117: 30 | J117: Good | K117: =(G117 - F117) / F117 -> 0.3 | L117: =IF(J117="bad", 1, 0) -> 0 | M117: =IF(C117=1, "1. First-Time Applicant", IF(C117<=3, "2. Early Repeat (2-3)", "3. High Velocity Loyalty (4+)")) -> 2. Early Repeat (2-3) | N117: =IFERROR(INDEX(Demographics!F:F, MATCH(A117, Demographics!A:A, 0)), "Unspecified Bank") -> GT Bank | O117: =IFERROR(INDEX(Demographics!H:H, MATCH(A117, Demographics!A:A, 0)) & "", "Unknown Status") -> Permanent
A118: 8a858fea5b391cd7015b3936e1ca25c8 | B118: 301960217 | C118: 5 | D118: 42918.786 | E118: 42918.744 | F118: 20000 | G118: 24500 | H118: 30 | J118: Good | K118: =(G118 - F118) / F118 -> 0.225 | L118: =IF(J118="bad", 1, 0) -> 0 | M118: =IF(C118=1, "1. First-Time Applicant", IF(C118<=3, "2. Early Repeat (2-3)", "3. High Velocity Loyalty (4+)")) -> 3. High Velocity Loyalty (4+) | N118: =IFERROR(INDEX(Demographics!F:F, MATCH(A118, Demographics!A:A, 0)), "Unspecified Bank") -> GT Bank | O118: =IFERROR(INDEX(Demographics!H:H, MATCH(A118, Demographics!A:A, 0)) & "", "Unknown Status") -> Permanent
...

Sheet Sheet4

Sheet Demographics
A1: customerid | B1: birthdate | C1: bank_account_type | D1: longitude_gps | E1: latitude_gps | F1: bank_name_clients | G1: bank_branch_clients | H1: employment_status_clients | I1: level_of_education_clients
A2: 8a858e135cb22031015cbafc76964ebd | B2: 26947 | C2: Savings | D2: 3.319219 | E2: 6.5286039 | F2: GT Bank
A3: 8a858e275c7ea5ec015c82482d7c3996 | B3: 31433 | C3: Savings | D3: 3.3255983 | E3: 7.1194033 | F3: Sterling Bank | H3: Permanent
A4: 8a858e5b5bd99460015bdc95cd485634 | B4: 31868 | C4: Savings | D4: 5.7460998 | E4: 5.5631737 | F4: Fidelity Bank
A5: 8a858efd5ca70688015cabd1f1e94b55 | B5: 33438 | C5: Savings | D5: 3.3628497 | E5: 6.6424853 | F5: GT Bank | H5: Permanent
A6: 8a858e785acd3412015acd48f4920d04 | B6: 30277 | C6: Savings | D6: 8.4553317 | E6: 11.97141 | F6: GT Bank | H6: Permanent
A7: 8a858f045bc9690c015bca251e9a4e95 | B7: 28835 | C7: Savings | D7: 3.3300869 | E7: 6.5525177 | F7: GT Bank | H7: Permanent
A8: 8a858ea05a859123015a8892914d15b7 | B8: 33075 | C8: Savings | D8: 3.365935 | E8: 6.5648233 | F8: Access Bank | H8: Permanent
A9: 8a858f275c451af5015c546a50ce55ed | B9: 31664 | C9: Savings | D9: 4.734382 | E9: 7.6068678 | F9: GT Bank | H9: Permanent
A10: 8a858f405d13c45f015d13dd93ec0c1c | B10: 33925 | C10: Savings | D10: 3.2905898 | E10: 6.6120747 | F10: EcoBank | H10: Permanent
A11: 8a858f735c161bda015c164d86632026 | B11: 23796 | C11: Savings | D11: 3.3627834 | E11: 6.5094178 | F11: EcoBank | H11: Permanent
A12: 8a858f2a5ce989dd015ce9fc24b1474b | B12: 34679 | C12: Savings | D12: 3.3502377 | E12: 7.1381618 | F12: FCMB
A13: 8a858f3a5c10828d015c109746d20aee | B13: 25768 | C13: Savings | D13: 5.768004 | E13: 5.559055 | F13: Skye Bank | H13: Permanent
A14: 8a858fb4563228d201564fd7519f22a8 | B14: 34488 | C14: Other | D14: 3.3810932 | E14: 6.608266 | F14: UBA | H14: Student | I14: Secondary
A15: 8a858e9d59e0997b0159eae2e4fa7611 | B15: 32472 | C15: Savings | D15: 3.3725099 | E15: 6.5181154 | F15: Zenith Bank
A16: 8a858f955a61ad4e015a69ee1edd0d3d | B16: 31517 | C16: Savings | D16: 3.357961 | E16: 6.5125169 | F16: GT Bank | H16: Permanent
A17: 8a858ff25a6a19ee015a6abff5ed659c | B17: 32499 | C17: Savings | D17: 7.5078362 | E17: 9.0483723 | F17: EcoBank | H17: Permanent
A18: 8a858e6c5c88d145015c894de1a91c5c | B18: 32255 | C18: Savings | D18: 3.363275 | E18: 7.1455067 | F18: GT Bank | H18: Permanent
A19: 8a858eb45876dcc501587dae11f2283e | B19: 32574 | C19: Savings | D19: 6.9744361 | E19: 4.8113433 | F19: Access Bank | H19: Permanent
A20: 8a858f2f54e28d530154ecdd303004fa | B20: 30444 | C20: Savings | D20: 3.4784832 | E20: 6.4420013 | F20: Diamond Bank | G20: LAGOS | H20: Permanent | I20: Graduate
A21: 8a858fef570f30e501571fd446d44c81 | B21: 31860 | C21: Savings | D21: 4.5684069 | E21: 7.5039585 | F21: GT Bank | H21: Self-Employed
A22: 8a858f6c570f2d660157238b0c4a1bdd | B22: 33057 | C22: Other | D22: 7.0408905 | E22: 5.7946838 | F22: Zenith Bank | H22: Self-Employed | I22: Graduate
A23: 8a85893d542e18bc01542e37365c120a | B23: 32161 | C23: Savings | D23: 3.3639265 | E23: 7.1380483 | F23: Zenith Bank | H23: Permanent | I23: Graduate
A24: 8a8588f35438fe12015444567666018e | B24: 30943 | C24: Other | D24: 11.13935 | E24: 10.292041 | F24: EcoBank | H24: Permanent
A25: 8a858f275c451af5015c49a2c43b5fb2 | B25: 31343 | C25: Savings | D25: 3.2987679 | E25: 6.6817293 | F25: Sterling Bank | H25: Permanent
A26: 8a858e045cd5b1d6015cd9c070a212a5 | B26: 31316 | C26: Savings | D26: 7.9028957 | E26: 8.8497435 | F26: UBA
A27: 8a858e2155defefd0155e12953ee00a1 | B27: 32668 | C27: Other | D27: 8.00851 | E27: 4.54539 | F27: First Bank | H27: Permanent | I27: Graduate
A28: 8a858e4b5a7f868b015a80f3822d505b | B28: 31992 | C28: Savings | D28: 3.3920645 | E28: 6.5083683 | F28: GT Bank | H28: Permanent
A29: 8a858f0056b7cf8e0156bbeefc4933cc | B29: 29593 | C29: Other | D29: 3.2943641 | E29: 6.5457472 | F29: EcoBank | H29: Self-Employed
A30: 8a858f0e5a6171ba015a648137c361bc | B30: 34218 | C30: Savings | D30: 3.385065 | E30: 6.5659733 | F30: GT Bank | H30: Permanent
A31: 8a858f125c5f88b1015c603d2810428c | B31: 30791 | C31: Savings | D31: 7.0481835 | E31: 4.8426899 | F31: GT Bank | H31: Permanent
A32: 8a858ee75a6156c0015a635f394a5f79 | B32: 30172 | C32: Savings | D32: 3.9395519 | E32: 7.4118193 | F32: Access Bank | H32: Permanent
A33: 8a858eed5af07cc4015af10da7565173 | B33: 27963 | C33: Savings | D33: 3.3553398 | E33: 6.5125031 | F33: GT Bank | H33: Permanent
A34: 8a858f445d41ebbe015d50c105334acc | B34: 31765 | C34: Savings | D34: 3.2148502 | E34: 6.538267 | F34: GT Bank
A35: 8a858f285d3ca5c4015d3cbb1f94073a | B35: 28335 | C35: Current | D35: 7.0358424 | E35: 4.8050149 | F35: GT Bank | H35: Permanent
A36: 8a858f225bfdb280015c108bf6f53281 | B36: 32057 | C36: Savings | D36: 3.3343336 | E36: 6.5223702 | F36: Union Bank | H36: Permanent
A37: 8a858f6c5cac8f53015cafeb15141be1 | B37: 33905 | C37: Savings | D37: 3.359517 | E37: 6.6106167 | F37: GT Bank | H37: Permanent
A38: 8a858f675c1c43bc015c2049f2d20224 | B38: 28019 | C38: Savings | D38: 3.4280578 | E38: 6.4323651 | F38: Access Bank | H38: Permanent
A39: 8a858f7e564ad338015654d3a5c242a5 | B39: 32282 | C39: Other | D39: 8.6713276 | E39: 9.0830135 | F39: GT Bank | H39: Permanent
A40: 8a858e165b90faf9015b9a873738471e | B40: 31922 | C40: Savings | D40: 3.9739724 | E40: 7.3727483 | F40: Access Bank | H40: Permanent
A41: 8a858ea4582fcdc80158338316a258e3 | B41: 29138 | C41: Other | D41: 5.1889972 | E41: 7.2826919 | F41: FCMB | H41: Permanent | I41: Graduate
A42: 8a858f3c5c16cadb015c177e274650b9 | B42: 27938 | C42: Savings | D42: 5.7936891 | E42: 5.5584987 | F42: Zenith Bank | H42: Permanent
A43: 8a858f2b5bf35819015bf3cc59193622 | B43: 31140 | C43: Savings | D43: 3.842152 | E43: 7.3284073 | F43: GT Bank | H43: Permanent
A44: 8a858ec555f82a230155f92ff37d0b31 | B44: 30335 | C44: Other | D44: 7.4104488 | E44: 9.1078476 | F44: Zenith Bank | H44: Self-Employed | I44: Post-Graduate
A45: 8a858f255cb1710a015cb56393f60d1b | B45: 26684 | C45: Savings | D45: 3.319583 | E45: 6.5694544 | F45: Skye Bank | H45: Permanent
A46: 8a858f6f5b3f095b015b4083532532a0 | B46: 33567 | C46: Savings | D46: 3.516056 | E46: 6.6697184 | F46: Access Bank | H46: Permanent
A47: 8a858fa257d8223c0157e7e6ce253dd8 | B47: 32419 | C47: Other | D47: 7.5113568 | E47: 9.1255927 | F47: Access Bank | H47: Permanent | I47: Graduate
A48: 8a858f335cd0c78e015cd435d7192800 | B48: 29789 | C48: Savings | D48: 2.957738 | E48: 6.5342122 | F48: GT Bank | H48: Permanent
A49: 8a858953548fb0c001549b31ac5f6dda | B49: 31103 | C49: Other | D49: 3.3767344 | E49: 6.5477946 | F49: Stanbic IBTC | H49: Unemployed | I49: Graduate
A50: 8a858eba5b681df4015b7b63e6ed6a23 | B50: 32320 | C50: Savings | D50: 3.4229723 | E50: 6.4652291 | F50: First Bank | H50: Permanent
A51: 8a858f8e5986f510015987965aa9183a | B51: 29037 | C51: Savings | D51: 3.3740957 | E51: 6.5991763 | F51: Diamond Bank | G51: LADIPO | H51: Permanent | I51: Secondary
A52: 8a858ee55cb156e6015cb650b14467f0 | B52: 34761 | C52: Savings | D52: 5.6085082 | E52: 6.4026569 | F52: First Bank | H52: Student
A53: 8a858f9157f7b9670157fa9d4e7546e0 | B53: 27232 | C53: Other | D53: 7.3977534 | E53: 5.1088625 | F53: First Bank | H53: Permanent
A54: 8a85883353d0c4e90153dfca251168bc | B54: 32567 | C54: Other | D54: 7.3592521 | E54: 9.0401384 | F54: GT Bank | H54: Self-Employed
A55: 8a858fa55acd8061015ad15eb8b47940 | B55: 32795 | C55: Savings | D55: 8.3475513 | E55: 4.9696443 | F55: Zenith Bank | H55: Permanent
A56: 8a8589a053acc39e0153b217f3d031cb | B56: 32173 | C56: Other | D56: 7.3814717 | E56: 9.170555 | F56: Standard Chartered | H56: Permanent
A57: 8a858e2e5bb57a37015bbe3c1af53cac | B57: 32857 | C57: Savings | D57: 3.57922 | E57: 7.9863467 | F57: GT Bank | H57: Permanent
A58: 8a8588c9548a33b201548b3cdb0f0c53 | B58: 32698 | C58: Savings | D58: -117.82251 | E58: 33.883619 | F58: GT Bank | H58: Permanent | I58: Graduate
A59: 8a858e345bd96da8015bdcde39b37570 | B59: 30547 | C59: Savings | D59: 5.6301086 | E59: 6.3376363 | F59: GT Bank
A60: 8a858e0f5c45466f015c4a6560255de7 | B60: 30463 | C60: Savings | D60: 3.3281894 | E60: 6.4662308 | F60: Stanbic IBTC | H60: Permanent
A61: 8a858fe758dc437a0158e524adb32ae2 | B61: 32960 | C61: Savings | D61: 7.4659083 | E61: 9.0777383 | F61: EcoBank | H61: Permanent
A62: 8a858e185b4923b4015b4ae48d28646a | B62: 31937 | C62: Savings | D62: 3.3965242 | E62: 6.6279429 | F62: GT Bank | H62: Permanent
A63: 8a858f725be8d4ff015bec5207ce5524 | B63: 31319 | C63: Savings | D63: 3.334732 | E63: 7.1176565 | F63: First Bank | H63: Permanent
A64: 8a858e2c5cc64f70015cc942825e71ae | B64: 31395 | C64: Savings | D64: 3.3831598 | E64: 6.6290094 | F64: GT Bank | H64: Permanent
A65: 8a858fbd5cd6054a015cda2ad0aa086d | B65: 32201 | C65: Savings | D65: 7.3362968 | E65: 5.1448074 | F65: UBA | H65: Permanent
A66: 8a858fba5cd5feee015cdb7d7d574f0f | B66: 26991 | C66: Savings | D66: 6.555882 | E66: 9.6033069 | F66: GT Bank | H66: Permanent
A67: 8a858fd85b685607015b75c2390b7173 | B67: 32134 | C67: Savings | D67: 3.2949932 | E67: 6.5583985 | F67: First Bank
A68: 8a858fe8555f401f0155679de3f04eb4 | B68: 31954 | C68: Other | D68: 3.8968769 | E68: 7.4179263 | F68: GT Bank | H68: Permanent
A69: 8a8589b953bc23f70153c887b4b45c9a | B69: 34012 | C69: Other | D69: 3.3144404 | E69: 6.6769796 | F69: GT Bank | H69: Permanent
A70: 8a858e935b496584015b496cdac50369 | B70: 33058 | C70: Savings | D70: 3.3882952 | E70: 6.596244 | F70: GT Bank | H70: Permanent
A71: 8a858e1d5b2510b2015b2c76fe45726a | B71: 24218 | C71: Savings | D71: 11.344892 | E71: 8.9465271 | F71: First Bank
A72: 8a76e7d443e6e97c0143ed0a1f4d5331 | B72: 28596 | C72: Other | D72: 3.4062008 | E72: 6.4437583 | F72: Access Bank | H72: Permanent | I72: Post-Graduate
A73: 8a8588bd5369b66d01536e7b60501609 | B73: 29010 | C73: Other | D73: 3.474824 | E73: 6.4343964 | F73: Zenith Bank | H73: Permanent | I73: Graduate
A74: 8a858f985b3db23f015b3ddf9cd73ed5 | B74: 30416 | C74: Savings | D74: 3.2924948 | E74: 6.5461386 | F74: GT Bank | H74: Permanent
A75: 8a858eae5c356262015c35894b181c1b | B75: 31065 | C75: Savings | D75: 7.438285 | E75: 10.544027 | F75: Fidelity Bank | H75: Permanent
A76: 8a858e6d5b252065015b2fa1ee3843da | B76: 31374 | C76: Savings | D76: 3.3808276 | E76: 6.6017004 | F76: GT Bank
A77: 8a858f6e5a951fc2015a9e8c2e4f4436 | B77: 27570 | C77: Savings | D77: 3.2932916 | E77: 6.6048079 | F77: Access Bank | H77: Permanent
A78: 8a858e2d5bc95851015bc98eb8fc1575 | B78: 31621 | C78: Savings | D78: 3.3771577 | E78: 6.6248323 | F78: GT Bank
A79: 8a858f6057e2dba50157f3558ac902d4 | B79: 31501 | C79: Other | D79: 7.2421228 | E79: 5.4917091 | F79: GT Bank | H79: Student | I79: Graduate
A80: 8a858e885c63d379015c730aa5f46f8b | B80: 31019 | C80: Savings | D80: 3.1545941 | E80: 6.4674226 | F80: First Bank | H80: Permanent
A81: 8a858e9156e137c601570b4d23a949fc | B81: 31718 | C81: Other | D81: 7.4115883 | E81: 10.42206 | F81: EcoBank | H81: Self-Employed
A82: 8a858fd35b5dfefb015b5e18a7ee15aa | B82: 31959 | C82: Savings | D82: 3.5833256 | E82: 6.4672584 | F82: First Bank | H82: Permanent
A83: 8a858eea5c82f136015c82f59f3201c7 | B83: 33023 | C83: Savings | D83: 3.374589 | E83: 7.1541192 | F83: Diamond Bank
A84: 8a858f305c8dd672015c9439eb1c6964 | B84: 33047 | C84: Savings | D84: 7.4643373 | E84: 9.0788447 | F84: UBA
A85: 8a858f7e5c69a6e3015c74334d791005 | B85: 32033 | C85: Savings | D85: 3.3211912 | E85: 6.5187057 | F85: GT Bank | H85: Permanent
A86: 8a858f8e597cf3f401598353f79a7171 | B86: 33052 | C86: Savings | D86: 3.3624968 | E86: 6.6620985 | F86: First Bank | H86: Permanent
A87: 8a858e6a5bfd4b54015c067c589f44c6 | B87: 26721 | C87: Savings | D87: 3.3981118 | E87: 7.1416558 | F87: GT Bank
A88: 8a858fa257d8223c0157e3c2a5e45d82 | B88: 33550 | C88: Other | D88: 7.485359 | E88: 9.0675955 | F88: GT Bank | H88: Permanent | I88: Graduate
A89: 8a8589005384ab570153880ceba74594 | B89: 28939 | C89: Other | D89: 3.4150101 | E89: 6.4442523 | F89: GT Bank | G89: AWOLOWO | H89: Permanent | I89: Graduate
A90: 8a8588dc536a1413015375acd19d4154 | B90: 32951 | C90: Savings | D90: 3.5115594 | E90: 6.437171 | F90: GT Bank | H90: Permanent
A91: 8a858e225c404292015c4f19fdfb148a | B91: 30325 | C91: Savings | D91: 3.3522491 | E91: 6.6335178 | F91: GT Bank | H91: Permanent
A92: 8a858e865bd4175e015bd85ed8ed6940 | B92: 33626 | C92: Savings | D92: 3.3617217 | E92: 6.5756123 | F92: GT Bank | H92: Permanent
A93: 8a858f73594ab1ea01595e72de584bca | B93: 31540 | C93: Savings | D93: -7.2394455 | E93: 54.998841 | F93: GT Bank | H93: Permanent
A94: 8a858eb4588604f701589b300e2768ee | B94: 31987 | C94: Savings | D94: 3.88588 | E94: 7.3360567 | F94: GT Bank | H94: Permanent
A95: 8a858ff5562dc3b601562e96135108e3 | B95: 34879 | C95: Other | D95: 7.3862093 | E95: 9.1091071 | F95: UBA | H95: Self-Employed
A96: 8a858fdc57b91cfc0157d2d576b01016 | B96: 33851 | C96: Savings | D96: 3.3027339 | E96: 6.6511226 | F96: GT Bank | G96: OGBA | H96: Student | I96: Graduate
A97: 8a858ef45cd09b8c015cd4d82f22728d | B97: 34742 | C97: Savings | D97: 3.376556 | E97: 6.5322733 | F97: Access Bank | H97: Permanent
A98: 8a858f1b5b256bc9015b2f7ff2d860fb | B98: 33935 | C98: Savings | D98: 5.0873216 | E98: 7.5618305 | F98: GT Bank | H98: Permanent
A99: 8a858f725b49c0c0015b4de5320b0e90 | B99: 31297 | C99: Savings | D99: 7.9020775 | E99: 8.8469304 | F99: GT Bank | H99: Unemployed
A100: 8a858fc75cd62882015ce0364fc515ca | B100: 29957 | C100: Savings | D100: 4.542942 | E100: 7.7841834 | F100: First Bank | H100: Permanent
...
